{
    "b13002": [
        {
            "hno": null,
            "id": "1",
            "nass": "§بَابٌ: أَوَّلُ مَا خَلَقَ اللَّهُ الْقَلَمُ",
            "page": "22",
            "part": "1",
            "seal": "0798C7CF"
        },
        {
            "hno": "1",
            "id": "2",
            "nass": "1 - حَدَّثَنَا عَبْدُ اللَّهِ بْنُ أَحْمَدَ بْنِ حَنْبَلٍ، حَدَّثَنَا أَحْمَدُ بْنُ جَمِيلٍ الْمَرْوَزِيُّ، حَدَّثَنَا عَبْدُ اللَّهِ بْنُ الْمُبَارَكِ، عَنْ رَبَاحِ بْنِ زَيْدٍ، عَنْ عُمَرَ بْنِ حَبِيبٍ، عَنِ الْقَاسِمِ بْنِ أَبِي بَزَّةَ، عَنْ سَعِيدِ بْنِ جُبَيْرٍ، عَنِ ابْنِ عَبَّاسٍ رَضِيَ اللَّهُ عَنْهُمَا قَالَ: قَالَ رَسُولُ اللَّهِ صَلَّى اللهُ عَلَيْهِ وَسَلَّمَ: \" §أَوَّلُ مَا خَلَقَ اللَّهُ الْقَلَمُ فَقَالَ لَهُ: اجْرِ. فَقَالَ: بِمَ أَجْرِي؟ فَقَالَ لَهُ: بِمَا هُوَ كَائِنٌ إِلَى يَوْمِ الْقِيَامَةِ \"",
            "page": "22",
            "part": "1",
            "seal": "6C02A6EF"
        },
        {
            "hno": null,
            "id": "3",
            "nass": "§بَابٌ: أَوَّلُ مَا خَلَقَ اللهُ مِنَ الْإِنْسَانِ فَرْجُهُ",
            "page": "24",
            "part": "1",
            "seal": "35AC15ED"
        },
        {
            "hno": "2",
            "id": "4",
            "nass": "2 - حَدَّثَنَا مُعَاذُ بْنُ الْمُثَنَّى، حَدَّثَنَا عَلِيُّ بْنُ الْمَدِينِيِّ، حَدَّثَنَا مُحَمَّدُ بْنُ فُضَيْلٍ، عَنْ لَيْثٍ، عَنْ مُجَاهِدٍ، عَنْ عَبْدِ اللَّهِ بْنِ عَمْرٍو قَالَ: \" §أَوَّلُ مَا خَلَقَ اللَّهُ مِنَ الْإِنْسَانِ فَرْجُهُ فَلَمَّا تَمَّ خَلْقُهُ قِيلَ لَهُ: لَا تُنْزِلْهُ إِلَّا فِي حِلِّهِ \"",
            "page": "24",
            "part": "1",
            "seal": "49150CDC"
        },
        {
            "hno": null,
            "id": "5",
            "nass": "§بَابُ أَنَّ أَوَّلَ مَنْ جَحَدَ آدَمُ عَلَيْهِ السَّلَامُ",
            "page": "25",
            "part": "1",
            "seal": "E7D011E9"
        },
        {
            "hno": "3",
            "id": "6",
            "nass": "3 - حَدَّثَنَا عَلِيُّ بْنُ عَبْدِ الْعَزِيزِ، حَدَّثَنَا حَجَّاجُ بْنُ الْمِنْهَالِ، حَدَّثَنَا حَمَّادُ بْنُ سَلَمَةَ، عَنْ عَلِيِّ بْنِ زَيْدِ بْنِ جُدْعَانَ، عَنْ يُوسُفَ بْنِ مِهْرَانَ، عَنِ ابْنِ عَبَّاسٍ رَضِيَ اللَّهُ عَنْهُمَا قَالَ: قَالَ رَسُولُ اللَّهِ صَلَّى اللهُ عَلَيْهِ وَسَلَّمَ: «§أَوَّلُ مَنْ جَحَدَ آدَمُ فَجَحَدَتْ ذُرِّيَّتُهُ»",
            "page": "25",
            "part": "1",
            "seal": "0306AE84"
        },
        {
            "hno": null,
            "id": "7",
            "nass": "§بَابُ أَنَا أَوَّلُ مَنْ تَنْشَقُّ عَنْهُ الْأَرْضُ يَوْمَ الْقِيَامَةِ",
            "page": "27",
            "part": "1",
            "seal": "19A9AE92"
        },
        {
            "hno": "4",
            "id": "8",
            "nass": "4 - حَدَّثَنَا عَبْدُ اللَّهِ بْنُ أَحْمَدَ بْنِ حَنْبَلٍ، حَدَّثَنَا هُدْبَةُ بْنُ خَالِدٍ، حَدَّثَنَا حَمَّادُ بْنُ سَلَمَةَ، عَنْ عَلِيِّ بْنِ زَيْدٍ، عَنْ أَبِي نَضْرَةَ، عَنِ ابْنِ عَبَّاسٍ قَالَ: قَالَ رَسُولُ اللَّهِ صَلَّى اللهُ عَلَيْهِ وَسَلَّمَ: «§أَنَا أَوَّلُ مَنْ تَنْشَقُّ عَنْهُ الْأَرْضُ يَوْمَ الْقِيَامَةِ»",
            "page": "27",
            "part": "1",
            "seal": "DDECD9AF"
        },
        {
            "hno": null,
            "id": "9",
            "nass": "§بَابُ أَنَا أَوَّلُ مَنْ يَقْرَعُ بَابَ الْجَنَّةِ",
            "page": "28",
            "part": "1",
            "seal": "6B94D8A0"
        },
        {
            "hno": "5",
            "id": "10",
            "nass": "5 - حَدَّثَنَا عُبَيْدُ بْنُ غَنَّامٍ الْكُوفِيُّ، حَدَّثَنَا أَبُو بَكْرِ بْنُ أَبِي شَيْبَةَ، حَدَّثَنَا مُعَاوِيَةُ بْنُ هِشَامٍ، حَدَّثَنَا سُفْيَانُ الثَّوْرِيُّ، عَنِ الْمُخْتَارِ بْنِ فُلْفُلٍ، عَنْ أَنَسِ بْنِ مَالِكٍ رَضِيَ اللَّهُ عَنْهُ قَالَ: قَالَ رَسُولُ اللَّهِ صَلَّى اللهُ عَلَيْهِ وَسَلَّمَ: «§أَنَا أَوَّلُ مَنْ يَقْرَعُ بَابَ الْجَنَّةِ»",
            "page": "28",
            "part": "1",
            "seal": "708386DB"
        },
        {
            "hno": null,
            "id": "11",
            "nass": "§بَابُ أَنَا أَوَّلُ شَافِعٍ وَأَوَّلُ مُشَفَّعٍ",
            "page": "30",
            "part": "1",
            "seal": "87BF418F"
        },
        {
            "hno": "6",
            "id": "12",
            "nass": "6 - حَدَّثَنَا أَحْمَدُ بْنُ عَبْدِ الْوَهَّابِ بْنِ نَجْدَةَ الْحَوْطِيُّ، حَدَّثَنَا مُحَمَّدُ بْنُ مُصْعَبٍ الْقَرْقَسَانِيُّ، حَدَّثَنَا الْأَوْزَاعِيُّ، عَنْ يَحْيَى بْنِ أَبِي كَثِيرٍ، عَنْ أَبِي سَلَمَةَ، عَنْ أَبِي هُرَيْرَةَ رَضِيَ اللَّهُ عَنْهُ قَالَ: قَالَ رَسُولُ اللَّهِ صَلَّى اللهُ عَلَيْهِ وَسَلَّمَ: «§أَنَا أَوَّلُ شَافِعٍ وَأَوَّلُ مُشَفَّعٍ»",
            "page": "30",
            "part": "1",
            "seal": "2FBA9921"
        },
        {
            "hno": null,
            "id": "13",
            "nass": "§بَابُ أَنَا أَوَّلُ شَافِعٍ وَأَوَّلُ مُشَفَّعٍ يَوْمَ الْقِيَامَةِ",
            "page": "32",
            "part": "1",
            "seal": "B37B13EA"
        },
        {
            "hno": null,
            "id": "14",
            "nass": "حَدَّثَنَا يَحْيَى بْنُ عُثْمَانَ بْنِ صَالِحٍ الْمِصْرِيُّ، حَدَّثَنَا أَبِي، حَدَّثَنَا بَكْرُ بْنُ مُضَرَ، عَنْ جَعْفَرِ بْنِ رَبِيعَةَ، عَنْ صَالِحِ بْنِ حَيَّانَ، عَنْ عَطَاءِ بْنِ أَبِي رَبَاحٍ، عَنْ جَابِرِ بْنِ عَبْدِ اللَّهِ قَالَ: قَالَ رَسُولُ اللَّهِ صَلَّى اللهُ عَلَيْهِ وَسَلَّمَ: «§أَنَا أَوَّلُ شَافِعٍ وَأَوَّلُ مُشَفَّعٍ يَوْمَ الْقِيَامَةِ»",
            "page": "32",
            "part": "1",
            "seal": "DD001064"
        },
        {
            "hno": null,
            "id": "15",
            "nass": "§بَابُ أَوَّلِ الْأُمَمِ يَدْخُلُ الْجَنَّةَ",
            "page": "32",
            "part": "1",
            "seal": "D8688E30"
        },
        {
            "hno": "8",
            "id": "16",
            "nass": "8 - حَدَّثَنَا مُحَمَّدُ بْنُ أَحْمَدَ بْنِ الْبَرَاءِ الْبَغْدَادِيُّ، حَدَّثَنَا عَبْدُ الْمُنْعِمِ بْنُ إِدْرِيسَ بْنِ سِنَانٍ، عَنْ أَبِيهِ، عَنْ وَهْبِ بْنِ مُنَبِّهٍ، عَنِ ابْنِ عَبَّاسٍ، وَجَابِرِ بْنِ عَبْدِ اللَّهِ، قَالَا: إِنَّ جِبْرِيلَ - عَلَيْهِ السَّلَامُ - قَالَ لِلنَّبِيِّ صَلَّى اللهُ عَلَيْهِ وَسَلَّمَ: «§أَوَّلُ الْأُمَمِ يَدْخُلُ الْجَنَّةَ أُمَّتُكَ»",
            "page": "32",
            "part": "1",
            "seal": "C0E6E1C9"
        },
        {
            "hno": null,
            "id": "17",
            "nass": "§بَابُ أَوَّلِ مَنْ يُكْسَى يَوْمَ الْقِيَامَةِ",
            "page": "33",
            "part": "1",
            "seal": "D0E4D3F8"
        },
        {
            "hno": "9",
            "id": "18",
            "nass": "9 - حَدَّثَنَا أَبُو مُسْلِمٍ الْكَجِّيُّ، حَدَّثَنَا مُحَمَّدُ بْنُ كَثِيرٍ الْعَبْدِيُّ، حَدَّثَنَا سُفْيَانُ الثَّوْرِيُّ، عَنِ الْمُغِيرَةِ بْنِ النُّعْمَانِ، عَنْ سَعِيدِ بْنِ جُبَيْرٍ، عَنِ ابْنِ عَبَّاسٍ عَنِ النَّبِيِّ صَلَّى اللهُ عَلَيْهِ وَسَلَّمَ قَالَ: «§أَوَّلُ مَنْ يُكْسَى يَوْمَ الْقِيَامَةِ خَلِيلُ اللَّهِ إِبْرَاهِيمُ عَلَيْهِ السَّلَامُ»",
            "page": "33",
            "part": "1",
            "seal": "AF2BCB96"
        },
        {
            "hno": null,
            "id": "19",
            "nass": "§بَابُ أَوَّلِ مَنْ أَضَافَ الضِّيفَانَ",
            "page": "35",
            "part": "1",
            "seal": "F3F7AC64"
        },
        {
            "hno": "10",
            "id": "20",
            "nass": "10 - حَدَّثَنَا أَحْمَدُ بْنُ عَمْرٍو الْخَلَّالُ الْمَكِّيُّ قَالَ: حَدَّثَنَا يَعْقُوبُ بْنُ حُمَيْدِ بْنِ كَاسِبٍ قَالَ: حَدَّثَنَا سَلَمَةُ بْنُ رَجَاءٍ، عَنْ مُحَمَّدِ بْنِ عَمْرِو بْنِ عَلْقَمَةَ، عَنْ أَبِي سَلَمَةَ، عَنْ أَبِي هُرَيْرَةَ رَضِيَ اللَّهُ عَنْهُ قَالَ: قَالَ رَسُولُ اللهِ صَلَّى اللهُ عَلَيْهِ وَسَلَّمَ: «§أَوَّلُ مَنْ أَضَافَ الْأَضْيَافَ إِبْرَاهِيمُ عَلَيْهِ السَّلَامُ»",
            "page": "35",
            "part": "1",
            "seal": "4E4654EB"
        },
        {
            "hno": null,
            "id": "21",
            "nass": "§بَابُ أَوَّلِ مَنِ اخْتُتِنَ",
            "page": "36",
            "part": "1",
            "seal": "92DA832E"
        },
        {
            "hno": "11",
            "id": "22",
            "nass": "11 - حَدَّثَنَا أَحْمَدُ بْنُ عَمْرٍو الْخَلَّالُ الْمَكِّيُّ، حَدَّثَنَا يَعْقُوبُ بْنُ حُمَيْدِ بْنِ كَاسِبٍ، حَدَّثَنَا سَلَمَةُ بْنُ رَجَاءٍ، عَنْ مُحَمَّدِ بْنِ عَمْرِو بْنِ عَلْقَمَةَ، عَنْ أَبِي سَلَمَةَ، عَنْ أَبِي هُرَيْرَةَ قَالَ: قَالَ رَسُولُ اللَّهِ صَلَّى اللهُ عَلَيْهِ وَسَلَّمَ: «§أَوَّلُ مَنِ اخْتُتِنَ إِبْرَاهِيمُ وَقَدْ أَتَتْ عَلَيْهِ مِائَةٌ وَعِشْرُونَ سَنَةً وَاخْتُتِنَ بِالْقَدُومِ» . الْقُدُومُ: مَوْضِعٌ بِالشَّامِ",
            "page": "36",
            "part": "1",
            "seal": "765FE23D"
        },
        {
            "hno": null,
            "id": "23",
            "nass": "§بَابُ أَوَّلِ مَنْ صُنِعَتْ لَهُ النُّورَةُ",
            "page": "37",
            "part": "1",
            "seal": "6A30107D"
        },
        {
            "hno": "12",
            "id": "24",
            "nass": "12 - حَدَّثَنَا أَحْمَدُ بْنُ خُلَيْدٍ الْحَلَبِيُّ، حَدَّثَنَا إِبْرَاهِيمُ بْنُ الْمَهْدِيِّ الْمِصِّيصِيُّ، حَدَّثَنَا عُمَرُ بْنُ عَبْدِ الرَّحْمَنِ أَبُو حَفْصٍ الْأَبَّارُ، حَدَّثَنَا إِسْمَاعِيلُ بْنُ عَبْدِ اللَّهِ الْكِنْدِيُّ، عَنْ أَبِي بُرْدَةَ، عَنْ أَبِي مُوسَى رَضِيَ اللَّهُ عَنْهُ قَالَ: قَالَ رَسُولُ اللَّهِ صَلَّى اللهُ عَلَيْهِ وَسَلَّمَ: \" §أَوَّلُ مَنْ صُنِعَتْ لَهُ النُّورَةُ وَدَخَلَ الْحَمَّامَ سُلَيْمَانُ بْنُ دَاوُدَ - عَلَيْهِمَا السَّلَامُ - فَلَمَّا دَخَلَ وَوَجَدَ حَرَّهُ قَالَ: أَوَّهْ مِنْ عَذَابِ اللَّهِ عَزَّ وَجَلَّ أَوَّهْ أَوَّهْ مِنْ قَبْلِ أَنْ لَا يَنْفَعُ أَوَّهْ \"",
            "page": "37",
            "part": "1",
            "seal": "48710074"
        },
        {
            "hno": null,
            "id": "25",
            "nass": "§بَابُ أَوَّلِ الْأَنْبِيَاءِ عَلَيْهِمُ السَّلَامُ",
            "page": "39",
            "part": "1",
            "seal": "8D250727"
        },
        {
            "hno": "13",
            "id": "26",
            "nass": "13 - حَدَّثَنَا أَحْمَدُ بْنُ أَنَسِ بْنِ مَالِكٍ الدِّمَشْقِيُّ، حَدَّثَنَا إِبْرَاهِيمُ بْنُ هِشَامِ بْنِ يَحْيَى بْنِ يَحْيَى الْغَسَّانِيُّ، حَدَّثَنِي أَبِي، عَنْ جَدِّي، عَنْ أَبِي إِدْرِيسَ الْخَوْلَانِيِّ، عَنْ أَبِي ذَرٍّ الْغِفَاريِّ رَضِيَ اللَّهُ عَنْهُ قَالَ: قَالَ رَسُولُ اللَّهِ صَلَّى اللهُ عَلَيْهِ وَسَلَّمَ: «§أَوَّلُ الْأَنْبِيَاءِ آدَمُ وَآخِرُهُمْ مُحَمَّدٌ صَلَّى اللهُ عَلَيْهِ وَسَلَّمَ وَعَلَيْهِمْ أَجْمَعِينَ»",
            "page": "39",
            "part": "1",
            "seal": "FFFB25D3"
        },
        {
            "hno": null,
            "id": "27",
            "nass": "§بَابُ أَوَّلِ مَنْ يُبْعَثُ يَوْمَ الْقِيَامَةِ مِنَ الْأُمَمِ وَأَوَّلُ مَنْ يُحَاسَبُ",
            "page": "40",
            "part": "1",
            "seal": "B0BEF6F2"
        },
        {
            "hno": "14",
            "id": "28",
            "nass": "14 - حَدَّثَنَا عَبْدُ اللَّهِ بْنُ أَحْمَدَ بْنِ حَنْبَلٍ، حَدَّثَنَا هُدْبَةُ بْنُ خَالِدٍ، حَدَّثَنَا حَمَّادُ بْنُ سَلَمَةَ، عَنْ عَلِيِّ بْنِ زَيْدٍ، عَنْ أَبِي نَضْرَةَ، عَنِ ابْنِ عَبَّاسٍ قَالَ: قَالَ رَسُولُ اللَّهِ صَلَّى اللهُ عَلَيْهِ وَسَلَّمَ: «§نَحْنُ أَوَّلُ مَنْ يُبْعَثُ وَأَوَّلُ مَنْ يُحَاسَبُ»",
            "page": "40",
            "part": "1",
            "seal": "32415520"
        },
        {
            "hno": null,
            "id": "29",
            "nass": "§بَابُ أَوَّلِ مَنْ صَافَحَ",
            "page": "41",
            "part": "1",
            "seal": "B71631C9"
        },
        {
            "hno": "15",
            "id": "30",
            "nass": "15 - حَدَّثَنَا مُعَاذُ بْنُ الْمُثَنَّى، حَدَّثَنَا عَلِيُّ بْنُ عُثْمَانَ اللَّاحَقَيُّ، حَدَّثَنَا حَمَّادُ بْنُ سَلَمَةَ، عَنْ حُمَيْدٍ، عَنْ أَنَسٍ قَالَ: قَالَ رَسُولُ اللَّهِ صَلَّى اللهُ عَلَيْهِ وَسَلَّمَ: «أَتَاكُمْ أَهْلُ الْيَمَنِ، هُمْ §أَرَقُّ النَّاسِ قُلُوبًا، وَهُمْ أَوَّلُ مَنْ حَيَّا بِالْمُصَافَحَةِ»",
            "page": "41",
            "part": "1",
            "seal": "4F6D5F33"
        },
        {
            "hno": null,
            "id": "31",
            "nass": "§بَابُ أَوَّلِ مَا بُدِئَ بِهِ رَسُولُ اللَّهِ مِنَ الْوَحْي",
            "page": "42",
            "part": "1",
            "seal": "49940B86"
        },
        {
            "hno": "16",
            "id": "32",
            "nass": "16 - حَدَّثَنَا إِسْحَاقُ بْنُ إِبْرَاهِيمَ، عَنْ عَبْدِ الرَّزَّاقِ، عَنْ مَعْمَرٍ، عَنِ الزُّهْرِيِّ، عَنْ عُرْوَةَ، عَنْ عَائِشَةَ رَضِيَ اللَّهُ عَنْهَا قَالَتْ: «§أَوَّلُ مَا بُدِئَ بِهِ رَسُولُ اللَّهِ صَلَّى اللهُ عَلَيْهِ وَسَلَّمَ مِنَ الْوَحْي الرُّؤْيَةُ الصَّادِقَةُ فَكَانَ لَا يَرَى رُؤْيَا إِلَّا جَاءَتْ مِثْلَ فَلَقِ الصُّبْحِ»",
            "page": "42",
            "part": "1",
            "seal": "CE08B0BD"
        },
        {
            "hno": null,
            "id": "33",
            "nass": "§بَابُ أَوَّلِ مَا نَزَلَ مِنَ الْقُرْآنِ",
            "page": "43",
            "part": "1",
            "seal": "DBE0A8AD"
        },
        {
            "hno": "17",
            "id": "34",
            "nass": "17 - حَدَّثَنَا حَفْصُ بْنُ عُمَرَ بْنِ الصَّبَّاحِ، حَدَّثَنَا عَبْدُ اللَّهِ بْنُ رَجَاءٍ، حَدَّثَنَا حَرْبُ بْنُ شَدَّادٍ، عَنْ يَحْيَى بْنِ أَبِي كَثِيرٍ، عَنْ أَبِي سَلَمَةَ، قَالَ: سَأَلْتُ جَابِرَ بْنَ عَبْدِ اللَّهِ: §أَيُّ الْقُرْآنِ أُنْزِلَ أَوَّلُ فَقَالَ: «يَا أَيُّهَا الْمُدَّثِّرُ»",
            "page": "43",
            "part": "1",
            "seal": "4F76FE0D"
        },
        {
            "hno": null,
            "id": "35",
            "nass": "§بَابُ أَوَّلِ مَا عَلَّمَ جِبْرِيلُ النَّبِيَّ صَلَّى اللهُ عَلَيْهِ وَسَلَّمَ",
            "page": "45",
            "part": "1",
            "seal": "5C77BE49"
        },
        {
            "hno": "18",
            "id": "36",
            "nass": "18 - حَدَّثَنَا يَحْيَى بْنُ عُثْمَانَ بْنِ صَالِحٍ الْمِصْرِيُّ، حَدَّثَنِي أَبِي، حَدَّثَنَا ابْنُ لَهِيعَةَ، عَنْ عَقِيلِ بْنِ خَالِدٍ، عَنِ الزُّهْرِيِّ، عَنْ عُرْوَةَ، عَنْ أُسَامَةَ بْنِ زَيْدٍ، عَنْ أَبِيهِ زَيْدِ بْنِ حَارِثَةَ قَالَ: «§أَوَّلُ مَا عَلَّمَ جِبْرِيلُ النَّبِيَّ صَلَّى اللهُ عَلَيْهِ وَسَلَّمَ الْوضُوءُ فَلَمَّا فَرَغَ أَخَذَ كَفًّا مِنْ مَاءٍ فَنَضَحَ بِهِ فَرْجَهُ»",
            "page": "45",
            "part": "1",
            "seal": "AF5E9727"
        },
        {
            "hno": null,
            "id": "37",
            "nass": "§بَابُ أَوَّلِ مَنْ سَيَّبَ السَّوَائِبَ وَبَحَرَ الْبَحِيرَةَ وَغَيَّرَ دِينَ إِبْرَاهِيمَ",
            "page": "46",
            "part": "1",
            "seal": "087953D1"
        },
        {
            "hno": "19",
            "id": "38",
            "nass": "19 - حَدَّثَنَا مُطَّلِبُ بْنُ شُعَيْبٍ الْأَزْدِيُّ، حَدَّثَنَا عَبْدُ اللَّهِ بْنُ صَالِحٍ، حَدَّثَنَا اللَّيْثُ بْنُ سَعْدٍ، عَنْ يَزِيدَ بْنِ عَبْدِ اللَّهِ بْنِ الْهَادِ، عَنِ الزُّهْرِيِّ، عَنْ سَعِيدِ بْنِ الْمُسَيِّبِ، عَنْ أَبِي هُرَيْرَةَ رَضِيَ اللَّهُ عَنْهُ قَالَ: قَالَ رَسُولُ اللَّهِ صَلَّى اللهُ عَلَيْهِ وَسَلَّمَ: \" §أَوَّلُ مَنْ سَيَّبَ السَّوَائِبَ وَبَحَرَ الْبَحِيرَةَ وَغَيَّرَ دِينَ إِبْرَاهِيمَ: عَمْرُو بْنُ لُحَيِّ بْنِ قَمْعَةَ بْنِ خِنْدِفِ بْنِ خُزَاعَةَ \"",
            "page": "46",
            "part": "1",
            "seal": "826BA75B"
        },
        {
            "hno": null,
            "id": "39",
            "nass": "§بَابُ أَوَّلِ مَا يَتَكَلَّمُ مِنَ الْإِنْسَانِ يَوْمَ الْقِيَامَةِ",
            "page": "47",
            "part": "1",
            "seal": "33F3F3D8"
        },
        {
            "hno": "20",
            "id": "40",
            "nass": "20 - حَدَّثَنَا إِدْرِيسُ بْنُ جَعْفَرٍ الْعَطَّارُ، حَدَّثَنَا يَزِيدُ بْنُ هَارُونَ، حَدَّثَنَا سَعِيدُ بْنُ إِيَاسَ، عَنْ حَكِيمِ بْنِ مُعَاوِيَةَ بْنِ حَيْدَةَ الْقُشَيْرِيِّ، عَنْ أَبِيهِ، عَنِ النَّبِيِّ صَلَّى اللهُ عَلَيْهِ وَسَلَّمَ قَالَ: «§أَوَّلُ مَا يَتَكَلَّمُ مِنَ الْإِنْسَانِ يَوْمَ الْقِيَامَةِ، وَيَشْهَدُ عَلَيْهِ بِعَمَلِهِ فَخِذُهُ وَكَفُّهُ»",
            "page": "47",
            "part": "1",
            "seal": "040422B9"
        },
        {
            "hno": null,
            "id": "41",
            "nass": "§بَابُ أَوَّلِ مَا يَنْطِقُ مِنَ الْإِنْسَانِ",
            "page": "48",
            "part": "1",
            "seal": "C7A44005"
        },
        {
            "hno": "21",
            "id": "42",
            "nass": "21 - حَدَّثَنَا إِدْرِيسُ بْنُ جَعْفَرٍ، حَدَّثَنَا يَزِيدُ بْنُ هَارُونَ، حَدَّثَنَا بَهْزُ بْنُ حَكِيمِ بْنِ مُعَاوِيَةَ، عَنْ أَبِيهِ، عَنْ جَدِّهِ قَالَ: قَالَ رَسُولُ اللَّهِ صَلَّى اللهُ عَلَيْهِ وَسَلَّمَ: «§إِنَّكُمْ تُعْرَضُونَ يَوْمَ الْقِيَامَةِ عَلَى أَفْوَاهِكُمُ الْفِدَامُ وَأَوَّلُ مَا يَنْطِقُ مِنَ الْإِنْسَانِ فَخِذُهُ وَيَدُهُ»",
            "page": "48",
            "part": "1",
            "seal": "BF086CBA"
        },
        {
            "hno": null,
            "id": "43",
            "nass": "§بَابُ أَوَّلِ مَا يُنْتِنُ مِنَ الْإِنْسَانِ فِي قَبْرِهِ",
            "page": "49",
            "part": "1",
            "seal": "7A187E95"
        },
        {
            "hno": "22",
            "id": "44",
            "nass": "22 - حَدَّثَنَا عَبْدُ اللَّهِ بْنُ أَحْمَدَ بْنِ حَنْبَلٍ، حَدَّثَنَا أَبُو كَامِلٍ الْفُضَيْلُ بْنُ حُسَيْنٍ الْجَحْدَرِيُّ، حَدَّثَنَا أَبُو عَوَانَةَ، عَنْ قَتَادَةَ، عَنِ الْحَسَنِ، عَنْ جُنْدُبِ بْنِ عَبْدِ اللَّهِ رَضِيَ اللَّهُ عَنْهُ قَالَ: سَمِعْتُ رَسُولَ اللَّهِ صَلَّى اللهُ عَلَيْهِ وَسَلَّمَ يَقُولُ: «مَنِ اسْتَطَاعَ مِنْكُمْ أَنْ لَا يُدْخِلَ بَطْنَهُ إِلَّا طَيِّبًا فَلْيَفْعَلْ فَإِنَّ §أَوَّلَ مَا يُنْتِنُ مِنَ الْإِنْسَانِ بَطْنُهُ»",
            "page": "49",
            "part": "1",
            "seal": "299218C1"
        },
        {
            "hno": null,
            "id": "45",
            "nass": "§بَابُ أَوَّلِ مَا يُحَاسَبُ بِهِ الْعَبْدُ",
            "page": "50",
            "part": "1",
            "seal": "70AFF6F3"
        },
        {
            "hno": "23",
            "id": "46",
            "nass": "23 - حَدَّثَنَا عَلِيُّ بْنُ عَبْدِ الْعَزِيزِ، حَدَّثَنَا حَجَّاجُ بْنُ الْمِنْهَالِ، حَدَّثَنَا حَمَّادُ بْنُ سَلَمَةَ، عَنْ دَاوُدَ بْنِ أَبِي هِنْدٍ، عَنْ زُرَارَةَ بْنِ أَوْفَى، عَنْ تَمِيمٍ الدَّارِيِّ رَضِيَ اللَّهُ عَنْهُ قَالَ: قَالَ رَسُولُ اللَّهِ صَلَّى اللهُ عَلَيْهِ وَسَلَّمَ: «§أَوَّلُ مَا يُحَاسَبُ بِهِ الْعَبْدُ الصَّلَاةُ فَإِنْ تَمَّتْ فَقَدْ أَفْلَحَ وَأَنْجَحَ وَإِنْ فَسَدَتْ فَقَدْ خَابَ وَخَسِرَ ثُمَّ سَائِرُ الْأَعْمَالِ»",
            "page": "50",
            "part": "1",
            "seal": "AF8E7BBC"
        },
        {
            "hno": null,
            "id": "47",
            "nass": "§بَابُ إِنَّ أَوَّلَ مَا يُقْضَى بِهِ بَيْنَ النَّاسِ فِي الدِّمَاءِ",
            "page": "52",
            "part": "1",
            "seal": "CF214DD5"
        },
        {
            "hno": "24",
            "id": "48",
            "nass": "24 - حَدَّثَنَا عُبَيْدُ بْنُ غَنَّامٍ، حَدَّثَنَا أَبُو بَكْرِ بْنُ أَبِي شَيْبَةَ، حَدَّثَنَا عَبْدَةُ بْنُ سُلَيْمَانَ، عَنِ الْأَعْمَشِ، عَنْ أَبِي وَائِلٍ، عَنْ عَبْدِ اللَّهِ عَنِ النَّبِيِّ صَلَّى اللهُ عَلَيْهِ وَسَلَّمَ قَالَ: «§أَوَّلُ مَا يُقْضَى بَيْنَ النَّاسِ فِي الدِّمَاءِ»",
            "page": "52",
            "part": "1",
            "seal": "09A8441B"
        },
        {
            "hno": null,
            "id": "49",
            "nass": "§بَابُ أَوَّلِ مَنْ رَمَى بِسَهْمٍ فِي سَبِيلِ اللَّهِ",
            "page": "53",
            "part": "1",
            "seal": "134E2393"
        },
        {
            "hno": "25",
            "id": "50",
            "nass": "25 - حَدَّثَنَا عُبَيْدُ بْنُ غَنَّامٍ، حَدَّثَنَا أَبُو بَكْرِ بْنُ أَبِي شَيْبَةَ، حَدَّثَنَا مُحَمَّدُ بْنُ أَبِي عُبَيْدَةَ بْنِ مَعْنٍ، عَنْ أَبِيهِ، عَنِ الْأَعْمَشِ، عَنْ أَبِي خَالِدٍ الْوَالِبِيِّ، عَنْ جَابِرِ بْنِ سَمُرَةَ، قَالَ: «§أَوَّلُ مَنْ رَمَى بِسَهْمٍ فِي سَبِيلِ اللَّهِ سَعْدُ بْنُ أَبِي وَقَّاصٍ»",
            "page": "53",
            "part": "1",
            "seal": "0A777B04"
        },
        {
            "hno": null,
            "id": "51",
            "nass": "§بَابُ أَوَّلِ مَنْ سَلَّ سَيْفًا فِي سَبِيلِ اللَّهِ تَعَالَى",
            "page": "54",
            "part": "1",
            "seal": "CE23AFBC"
        },
        {
            "hno": "26",
            "id": "52",
            "nass": "26 - حَدَّثَنَا أَبُو يَزِيدَ الْقَرَاطِيسِيُّ يُوسُفُ بْنُ يَزِيدَ، حَدَّثَنَا أَسَدُ بْنُ مُوسَى، حَدَّثَنَا عَبْدَةُ بْنُ سُلَيْمَانَ، عَنْ هِشَامِ بْنِ عُرْوَةَ، عَنْ أَبِيهِ، قَالَ: \" §أَوَّلُ مَنْ سَلَّ سَيْفًا فِي سَبِيلِ اللَّهِ: الزُّبَيْرُ بْنُ الْعَوَّامِ، كَانَ فِي دَارِهِ بِمَكَّةَ فَبَلَغَهُ أَنَّ نَاسًا مِنَ الْمُشْرِكِينَ أَرَادُوا أَنْ يَفْتِكُوا بِرَسُولِ اللَّهِ صَلَّى اللهُ عَلَيْهِ وَسَلَّمَ فَسَلَّ سَيْفَهُ وَخَرَجَ فِي طَلَبِهِ \"",
            "page": "54",
            "part": "1",
            "seal": "0D91AA50"
        },
        {
            "hno": null,
            "id": "53",
            "nass": "§بَابُ أَوَّلِ مَنْ قَدِمَ الْمَدِينَةَ مِنَ الْمُهَاجِرِينَ",
            "page": "55",
            "part": "1",
            "seal": "17B60BCD"
        },
        {
            "hno": "27",
            "id": "54",
            "nass": "27 - حَدَّثَنَا عَلِيُّ بْنُ عَبْدِ الْعَزِيزِ، حَدَّثَنَا عَبْدُ اللَّهِ بْنُ رَجَاءٍ، حَدَّثَنَا إِسْرَائِيلُ، عَنْ أَبِي إِسْحَاقَ، عَنِ الْبَرَاءِ بْنِ عَازِبٍ رَضِيَ اللَّهُ عَنْهُمَا قَالَ: \" كَانَ §أَوَّلَ مَنْ قَدِمَ عَلَيْنَا مِنَ الْمُهَاجِرِينَ مُصْعَبُ بْنُ عُمَيْرٍ أَخِي بَنِي عَبْدِ الدَّارِ بْنِ قُصَيٍّ فَقُلْنَا: مَا فَعَلَ مَنْ وَرَاءَكَ؟ مَا فَعَلَ رَسُولُ اللَّهِ صَلَّى اللهُ عَلَيْهِ وَسَلَّمَ؟ قَالَ: هُوَ مَكَانَهُ \"",
            "page": "55",
            "part": "1",
            "seal": "06454D94"
        },
        {
            "hno": null,
            "id": "55",
            "nass": "§بَابُ أَوَّلِ مَنْ جَمَّعَ بِالْمَدِينَةِ قَبْلَ قُدُومِ رَسُولِ اللَّهِ",
            "page": "56",
            "part": "1",
            "seal": "3422462E"
        },
        {
            "hno": "28",
            "id": "56",
            "nass": "28 - حَدَّثَنَا مُحَمَّدُ بْنُ الْوَلِيدِ النَّرْسِيُّ، حَدَّثَنَا مُحَمَّدُ بْنُ الْمُثَنَّى أَبُو مُوسَى، حَدَّثَنَا يَحْيَى بْنُ كَثِيرٍ الْعَنْبَرِيُّ، حَدَّثَنَا صَالِحٌ الْعَنْبَرِيُّ، حَدَّثَنَا صَالِحُ بْنُ أَبِي الْأَخْضَرِ، عَنِ الزُّهْرِيِّ، عَنْ أَبِي بَكْرِ بْنِ عَبْدِ الرَّحْمَنِ بْنِ الْحَارِثِ بْنِ هِشَامٍ، عَنْ عُقْبَةَ بْنِ عَمْرٍو أَبِي مَسْعُودٍ الْأَنْصَارِيِّ رَضِيَ اللَّهُ عَنْهُ قَالَ: «§أَوَّلُ مَنْ جَمَّعَ بِالْمَدِينَةِ قَبْلَ أَنْ يَقْدُمَ النَّبِيُّ صَلَّى اللهُ عَلَيْهِ وَسَلَّمَ مُصْعَبُ بْنُ عُمَيْرٍ»",
            "page": "56",
            "part": "1",
            "seal": "D3A2B405"
        },
        {
            "hno": null,
            "id": "57",
            "nass": "§بَابُ أَوَّلِ جُمُعَةٍ جُمِّعَتْ فِي الْإِسْلَامِ فِي غَيْرِ الْمَدِينَةِ",
            "page": "57",
            "part": "1",
            "seal": "8949CCCF"
        },
        {
            "hno": "29",
            "id": "58",
            "nass": "29 - حَدَّثَنَا مُحَمَّدُ بْنُ عَلِيٍّ الصَّائِغُ الْمَكِّيُّ، حَدَّثَنَا الْحَسَنُ بْنُ عَلِيٍّ الْحُلْوَانِيُّ، حَدَّثَنَا يَحْيَى بْنُ آدَمَ، حَدَّثَنَا يَزِيدُ بْنُ عَبْدِ الْعَزِيزِ بْنِ سِيَاهٍ، عَنْ مُحَمَّدِ بْنِ أَبِي حَفْصَةَ، عَنْ أَبِي جَمْرَةَ، عَنِ ابْنِ عَبَّاسٍ قَالَ: \" §أَوَّلُ جُمُعَةٍ جُمِّعَتْ بَعْدَ جُمُعَةٍ بِالْمَدِينَةِ جُمُعَةٌ بِالْبَحْرَيْنِ فِي قَرْيَةٍ لِعَبْدِ الْقَيْسِ يُقَالُ لَهَا: جُوَاثَا \"",
            "page": "57",
            "part": "1",
            "seal": "6FCDD091"
        },
        {
            "hno": null,
            "id": "59",
            "nass": "§بَابُ أَوَّلِ آيَةٍ نَزَلَتْ فِي الْقِتَالِ",
            "page": "58",
            "part": "1",
            "seal": "43317D7B"
        },
        {
            "hno": "30",
            "id": "60",
            "nass": "30 - حَدَّثَنَا مَحْمُودُ بْنُ مُحَمَّدٍ الْوَاسِطِيُّ، حَدَّثَنَا زَكَرِيَّا بْنُ يَحْيَى رَحْمَوَيْهِ، حَدَّثَنَا إِسْحَاقُ بْنُ يُوسُفَ الْأَزْرَقُ، عَنْ سُفْيَانَ الثَّوْرِيِّ، عَنِ الْأَعْمَشِ، عَنْ مُسْلِمٍ الْبَطِينِ، عَنْ سَعِيدِ بْنِ جُبَيْرٍ، عَنِ ابْنِ عَبَّاسٍ قَالَ: لَمَّا أُخْرِجَ النَّبِيُّ صَلَّى اللهُ عَلَيْهِ وَسَلَّمَ مِنْ مَكَّةَ قَالَ أَبُو بَكْرٍ: «إِنَّا لِلَّهِ وَإِنَّا إِلَيْهِ رَاجِعُونَ أَخْرَجُوا نَبِيَّهُمْ لَيَهْلِكُنَّ» فَنَزَلَتْ هَذِهِ الْآيَةُ {أُذِنَ لِلَّذِينَ يُقَاتَلُونَ بِأَنَّهُمْ ظُلِمُوا وَإِنَّ اللَّهَ عَلَى نَصْرِهِمْ لَقَدِيرٌ. .} [الحج: 39] قَالَ: «فَعَرَفْتُ أَنَّهُ سَيَكُونُ قِتَالٌ» . قَالَ ابْنُ عَبَّاسٍ: «§وَهِيَ أَوَّلُ آيَةٍ نَزَلَتْ فِي الْقِتَالِ»",
            "page": "58",
            "part": "1",
            "seal": "406A5529"
        },
        {
            "hno": null,
            "id": "61",
            "nass": "§بَابُ أَوَّلِ زُمْرَةٍ يَدْخُلُونَ الْجَنَّةَ",
            "page": "59",
            "part": "1",
            "seal": "5C6B232B"
        },
        {
            "hno": "31",
            "id": "62",
            "nass": "31 - حَدَّثَنَا مُحَمَّدُ بْنُ زَكَرِيَّا الْغِلَابِيُّ، حَدَّثَنَا أَبُو هَمَّامٍ مُحَمَّدُ بْنُ مُحَبَّبٍ الدَّلَّالُ، حَدَّثَنَا سُفْيَانُ بْنُ سَعِيدٍ الثَّوْرِيُّ، عَنِ الْأَعْمَشِ، عَنْ أَبِي صَالِحٍ، عَنْ أَبِي هُرَيْرَةَ قَالَ: قَالَ رَسُولُ اللَّهِ صَلَّى اللهُ عَلَيْهِ وَسَلَّمَ: «§أَوَّلُ زُمْرَةٍ تَدْخُلُ الْجَنَّةَ عَلَى صُورَةِ الْقَمَرِ لَيْلَةَ الْبَدْرِ ثُمَّ الَّذِينَ يَلُونَهُمْ عَلَى أَشَدِّ نَجْمٍ فِي السَّمَاءِ إِضَاءَةً ثُمَّ هُمْ بَعْدُ مَنَازِلُ وَلَا يَبُولُونَ وَلَا يَتَغَوَّطُونَ وَلَا يَمْتَخِطُونَ وَلَا يَتْفُلُونَ، أَمْشَاطُهُمُ الذَّهَبُ، وَمَجَامِرُهُمُ الْأَلُوَّةُ وَرَشْحُهُمُ الْمِسْكُ وَخَلْقُهُمْ عَلَى خَلْقِ رَجُلٍ وَاحِدٍ عَلَى صُورَةِ أَبِيهِمْ آدَمَ - عَلَيْهِ السَّلَامُ - سِتُّونَ ذِرَاعًا»",
            "page": "59",
            "part": "1",
            "seal": "436DCFBC"
        },
        {
            "hno": null,
            "id": "63",
            "nass": "§بَابُ إِنَّ أَوَّلَ الْآيَاتِ طُلُوعُ الشَّمْسِ مِنْ مَغْرِبِهَا",
            "page": "60",
            "part": "1",
            "seal": "940C1CAF"
        },
        {
            "hno": "32",
            "id": "64",
            "nass": "32 - حَدَّثَنَا عَلِيُّ بْنُ عَبْدِ الْعَزِيزِ، حَدَّثَنَا أَبُو حُذَيْفَةَ، حَدَّثَنَا سُفْيَانُ الثَّوْرِيُّ، عَنْ أَبِي حَيَّانَ التَّيْمِيِّ، عَنْ أَبِي زُرْعَةَ بْنِ عَمْرِو بْنِ جَرِيرٍ، عَنْ عَبْدِ اللَّهِ بْنِ عُمَرَ رَضِيَ اللَّهُ عَنْهُمَا: عَنِ النَّبِيِّ صَلَّى اللهُ عَلَيْهِ وَسَلَّمَ قَالَ: \" §أَوَّلُ الْآيَاتِ: طُلُوعُ الشَّمْسِ مِنْ مَغْرِبِهَا وَخُرُوجُ الدَّابَّةِ عَلَى النَّاسِ ضُحًى فَأَيَّتُهُمَا كَانَتْ قَبْلُ كَانَتِ الْأُخْرَى عَلَى أَثَرِهَا قَرِيبًا \"",
            "page": "60",
            "part": "1",
            "seal": "D8D96D1F"
        },
        {
            "hno": null,
            "id": "65",
            "nass": "§بَابُ أَوَّلِ مَنْ قُطِعَ فِي الْإِسْلَامِ",
            "page": "61",
            "part": "1",
            "seal": "CB6A73BE"
        },
        {
            "hno": "33",
            "id": "66",
            "nass": "33 - حَدَّثَنَا إِسْحَاقُ بْنُ إِبْرَاهِيمَ الدَّبَرِيُّ، عَنْ عَبْدِ الرَّزَّاقِ، عَنْ سُفْيَانَ الثَّوْرِيِّ، عَنْ يَحْيَى بْنِ عَبْدِ اللَّهِ التَّيْمِيِّ، عَنْ أَبِي مَاجِدٍ الْحَنَفِيِّ، عَنْ عَبْدِ اللَّهِ بْنِ مَسْعُودٍ رَضِيَ اللَّهُ عَنْهُ قَالَ: إِنَّ أَوَّلَ رَجُلٍ مِنَ الْمُسْلِمِينَ قُطِعَ فِي الْإِسْلَامِ رَجُلٌ مِنَ الْأَنْصَارِ فَقِيلَ: يَا رَسُولَ اللَّهِ هَذَا سَرَقَ فَكَأَنَّمَا سُفَّ فِي وَجْهِ رَسُولِ اللَّهِ الرَّمَادُ. فَقَالَ بَعْضُهُمْ: يَا رَسُولَ اللَّهِ سُفَّ عَلَيْكَ فَقَالَ: \" وَمَا يَمْنَعُنِي وَأَنْتُمْ أَعْوَانُ الشَّيْطَانِ عَلَى أَخِيكُمْ ثُمَّ قَالَ: §إِنَّ اللَّهَ عَفُوٌّ يُحِبُّ الْعَفْوَ فَلَا يَنْبَغِي لِوَالٍ أَنْ يُؤْتَى بِحَدٍّ إِلَّا أَقَامَهُ. ثُمَّ قَرَأَ {وَلْيَعْفُوا وَلْيَصْفَحُوا، أَلَا تُحِبُّونَ أَنْ يَغْفِرَ اللَّهُ لَكُمْ وَاللَهُ غَفُورٌ رَحِيمٌ} [النور: 22] \"",
            "page": "61",
            "part": "1",
            "seal": "D8D2A80A"
        },
        {
            "hno": null,
            "id": "67",
            "nass": "§بَابُ أَوَّلِ مَا سُمِعَ مِنَ رَسُولِ اللَّهِ حِينَ قَدِمَ الْمَدِينَةَ",
            "page": "62",
            "part": "1",
            "seal": "4ED4DCDF"
        },
        {
            "hno": "34",
            "id": "68",
            "nass": "34 - حَدَّثَنَا بِشْرُ بْنُ مُوسَى، حَدَّثَنَا هَوْذَةُ بْنُ خَلِيفَةَ الْبَكْرَاوِيُّ، حَدَّثَنَا عَوْفٌ الْأَعْرَابِيُّ، عَنْ زُرَارَةَ بْنِ أَوْفَى، عَنْ عَبْدِ اللَّهِ بْنِ سَلَامٍ رَضِيَ اللَّهُ عَنْهُ قَالَ: لَمَّا قَدِمَ رَسُولُ اللَّهِ صَلَّى اللهُ عَلَيْهِ وَسَلَّمَ انْجَفَلَ النَّاسُ قِبَلَهُ فَكُنْتُ فِيمَنْ خَرَجَ فَكَانَ أَوَّلُ مَا سَمِعْتُهُ يَقُولُ: «§أَطْعِمُوا الطَّعَامَ وَأَفْشُوا السَّلَامَ وَصِلُوا الْأَرْحَامَ وَصَلُّوا بِاللَّيْلِ وَالنَّاسُ نِيَامٌ تَدْخُلُوا الْجَنَّةَ بِسَلَامٍ»",
            "page": "62",
            "part": "1",
            "seal": "C29139EC"
        },
        {
            "hno": null,
            "id": "69",
            "nass": "§بَابُ أَوَّلِ مَنْ جَدَّرَ الْكَعْبَةَ بَعْدَ كِلَابِ بْنِ مُرَّةَ",
            "page": "63",
            "part": "1",
            "seal": "3410C129"
        },
        {
            "hno": "35",
            "id": "70",
            "nass": "35 - حَدَّثَنَا أَبُو زُرْعَةَ الدِّمَشْقِيُّ، حَدَّثَنَا أَبُو الْيَمَانِ الْحَكَمُ بْنُ نَافِعٍ، حَدَّثَنَا إِسْمَاعِيلُ بْنُ عَيَّاشٍ، عَنْ عَبْدِ الْعَزِيزِ بْنِ عُبَيْدِ اللَّهِ، عَنْ عَبْدِ اللَّهِ بْنِ يَزِيدَ مَوْلَى الْمُنْبَعِثِ، عَنْ أَبِي سَعِيدٍ الْخُدْرِيِّ رَضِيَ اللَّهُ عَنْهُ قَالَ: قَالَ رَسُولُ اللَّهِ صَلَّى اللهُ عَلَيْهِ وَسَلَّمَ: «§قُصَيٌّ أَوَّلُ مَنْ جَدَّرَ الْكَعْبَةَ بَعْدَ كِلَابِ بْنِ مُرَّةَ»",
            "page": "63",
            "part": "1",
            "seal": "DB0EBDA4"
        },
        {
            "hno": null,
            "id": "71",
            "nass": "§بَابُ أَوَّلِ مَنْ يَدْخُلُ النَّارَ مِنْ هَذِهِ الْأُمَّةِ",
            "page": "64",
            "part": "1",
            "seal": "EF37F9A1"
        },
        {
            "hno": "36",
            "id": "72",
            "nass": "36 - حَدَّثَنَا أَحْمَدُ بْنُ مُطَيَّرٍ الرَّمْلِيِّ الْقَاضِي، حَدَّثَنَا مُحَمَّدُ بْنُ أَبِي السَّرِيِّ الْعَسْقَلَانِيُّ، حَدَّثَنَا ضَمْرَةُ بْنُ رَبِيعَةَ، عَنِ ابْنِ شَوْذَبٍ، عَنْ أَبِي الْمُهَزَّمِ، عَنْ أَبِي هُرَيْرَةَ قَالَ: «§أَوَّلُ مَنْ يَدْخُلُ النَّارَ مِنْ هَذِهِ الْأُمَّةِ السَّوَّاطُونَ»",
            "page": "64",
            "part": "1",
            "seal": "8041AA78"
        },
        {
            "hno": null,
            "id": "73",
            "nass": "§بَابُ أَوَّلِ مَنْ يُكْسَى حُلَّةً مِنَ النَّارِ",
            "page": "65",
            "part": "1",
            "seal": "00A061CE"
        },
        {
            "hno": "37",
            "id": "74",
            "nass": "37 - حَدَّثَنَا عَلِيُّ بْنُ عَبْدِ الْعَزِيزِ، حَدَّثَنَا حَجَّاجُ بْنُ الْمِنْهَالِ، حَدَّثَنَا حَمَّادُ بْنُ سَلَمَةَ، عَنْ عَلِيِّ بْنِ زَيْدِ بْنِ جُدْعَانَ: عَنِ النَّبِيِّ صَلَّى اللهُ عَلَيْهِ وَسَلَّمَ قَالَ: «§أَوَّلُ مَنْ يُكْسَى حُلَّةً مِنَ النَّارِ إِبْلِيسُ لَعَنَهُ اللَّهُ»",
            "page": "65",
            "part": "1",
            "seal": "FC3ADE6B"
        },
        {
            "hno": null,
            "id": "75",
            "nass": "§بَابُ أَوَّلِ مَنْ يَرِدُ عَلَى النَّبِيِّ حَوْضَهُ",
            "page": "66",
            "part": "1",
            "seal": "211F543D"
        },
        {
            "hno": "38",
            "id": "76",
            "nass": "38 - حَدَّثَنَا يَحْيَى بْنُ عُثْمَانَ بْنِ صَالِحٍ الْوُحَاظِيُّ، حَدَّثَنَا نُعَيْمُ بْنُ حَمَّادٍ الْمَرْوَزِيُّ، حَدَّثَنَا مُحَمَّدُ بْنُ فُضَيْلٍ، عَنِ السَّرِيِّ بْنِ إِسْمَاعِيلَ، عَنِ الشَّعْبِيِّ، عَنْ سُفْيَانَ بْنِ اللَّيْلِ، عَنِ الْحَسَنِ بْنِ عَلِيِّ بْنِ أَبِي طَالِبٍ رَضِيَ اللَّهُ عَنْهُ قَالَ: سَمِعْتُ رَسُولَ اللَّهِ صَلَّى اللهُ عَلَيْهِ وَسَلَّمَ يَقُولُ: «§أَوَّلُ مَنْ يَرِدُ حَوْضِي أَهْلُ بَيْتِي وَمَنْ أَحَبَّنِي مِنْ أُمَّتِي»",
            "page": "66",
            "part": "1",
            "seal": "AD1EB48D"
        },
        {
            "hno": null,
            "id": "77",
            "nass": "§بَابُ أَوَّلِ مَنْ يَرِدُ الْحَوْضَ بَعْدَ هَذِهِ الطَّبَقَةِ",
            "page": "67",
            "part": "1",
            "seal": "E5C3FF62"
        },
        {
            "hno": "39",
            "id": "78",
            "nass": "39 - حَدَّثَنَا أَحْمَدُ بْنُ خُلَيْدٍ، حَدَّثَنَا أَبُو تَوْبَةَ الرَّبِيعُ بْنُ نَافِعٍ، حَدَّثَنَا مُحَمَّدُ بْنُ مُهَاجِرٍ، عَنِ الْعَبَّاسِ بْنِ سَالِمٍ، عَنْ أَبِي سَلَّامٍ الْحَبَشِيِّ، عَنْ ثَوْبَانَ مَوْلَى رَسُولِ اللَّهِ صَلَّى اللهُ عَلَيْهِ وَسَلَّمَ قَالَ: قَالَ رَسُولُ اللَّهِ صَلَّى اللهُ عَلَيْهِ وَسَلَّمَ: «§حَوْضِي مَا بَيْنَ عَدَنَ إِلَى عُمَانَ الْبَلْقَاءِ أَحْلَى مِنَ الْعَسَلِ وَأَطْيَبُ مِنَ الْمِسْكِ وَأَبْيَضُ مِنَ اللَّبَنِ أَكْوَابُهُ عَدَدُ نُجُومِ السَّمَاءِ. مَنْ شَرِبَ مِنْهُ شَرْبَةً لَمْ يَظْمَأْ بَعْدَهَا أَبَدًا. أَوَّلُ النَّاسِ يَرِدُ عَلَيْهِ فُقَرَاءُ الْمُهَاجِرِينَ الشُّعْثُ رُؤُوسًا الدُّنْسُ ثِيَابًا الَّذِينَ لَا يَنْكِحُونَ الْمُتَنَعِّمَاتِ وَلَا تُفْتَحُ لَهُمُ السُّدَدُ»",
            "page": "67",
            "part": "1",
            "seal": "F306448D"
        },
        {
            "hno": null,
            "id": "79",
            "nass": "§بَابُ أَوَّلِ مَنْ قَالَ أَمَا بَعْدُ",
            "page": "68",
            "part": "1",
            "seal": "EAD66D61"
        },
        {
            "hno": "40",
            "id": "80",
            "nass": "40 - حَدَّثَنَا جَعْفَرُ بْنُ سُلَيْمَانَ النَّوْفَلِيُّ الْمَدَنِيُّ، حَدَّثَنَا إِبْرَاهِيمُ بْنُ الْمُنْذِرِ الْحِزَامِيُّ، حَدَّثَنَا عَبْدُ الْعَزِيزِ بْنُ أَبِي ثَابِتٍ، عَنْ عَبْدِ الرَّحْمَنِ بْنِ أَبِي الزِّنَادِ، عَنْ أَبِيهِ، عَنْ بِلَالِ بْنِ أَبِي بُرْدَةَ، عَنْ أَبِي بُرْدَةَ، عَنْ أَبِي مُوسَى رَضِيَ اللَّهُ عَنْهُ: عَنِ النَّبِيِّ صَلَّى اللهُ عَلَيْهِ وَسَلَّمَ قَالَ: \" §أَوَّلُ مَنْ قَالَ: أَمَّا بَعْدُ: دَاوُدُ النَّبِيُّ عَلَيْهِ السَّلَامُ. وَهُوَ فَصْلُ الْخِطَابِ \"",
            "page": "68",
            "part": "1",
            "seal": "6EAFB476"
        },
        {
            "hno": null,
            "id": "81",
            "nass": "§بَابُ أَوَّلِ مَنْ كَتَبَ بِسْمِ اللَّهِ الرَّحْمَنِ الرَّحِيمِ",
            "page": "69",
            "part": "1",
            "seal": "F0D60D5F"
        },
        {
            "hno": "41",
            "id": "82",
            "nass": "41 - حَدَّثَنَا عَمْرُو بْنُ أَبِي طَاهِرِ بْنِ السَّرْحِ، حَدَّثَنَا أَبِي، حَدَّثَنَا مُوسَى بْنُ عَبْدِ الرَّحْمَنِ الصَّنْعَانِيُّ، عَنِ ابْنِ جُرَيْجٍ، عَنْ عَطَاءٍ، عَنِ ابْنِ عَبَّاسٍ قَالَ: «§أَوَّلُ مَنْ كَتَبَ بِسْمِ اللَّهِ الرَّحْمَنِ الرَّحِيمِ سُلَيْمَانُ عَلَيْهِ السَّلَامُ»",
            "page": "69",
            "part": "1",
            "seal": "B160599B"
        },
        {
            "hno": null,
            "id": "83",
            "nass": "حَدَّثَنَا عَلِيُّ بْنُ عَبْدِ الْعَزِيزِ، حَدَّثَنَا أَبُو عُبَيْدٍ الْقَاسِمُ بْنُ سَلَّامٍ، حَدَّثَنَا حَجَّاجُ بْنُ مُحَمَّدٍ، عَنِ ابْنِ جُرَيْجِ قَالَ: \" §مَا زَادَ سُلَيْمَانُ بْنُ دَاوُدَ عَلَيْهِ السَّلَامُ فِي كِتَابِهِ عَلَى مَا قَالَ اللَّهُ عَزَّ وَجَلَّ: {إِنَّهُ مِنْ سُلَيْمَانَ وَإِنَّهُ بِسْمِ اللَّهِ الرَّحْمَنِ الرَّحِيمِ أًلَّا تَعْلُوا عَلَي وَأْتُونِي مُسْلِمَيْنِ} [النمل: 31] \"",
            "page": "70",
            "part": "1",
            "seal": "AD07FC57"
        },
        {
            "hno": null,
            "id": "84",
            "nass": "§بَابُ أَوَّلُ مَا كَانَ يُلْقِي جِبْرِيلُ عَلَى رَسُولِ اللَّهِ صَلَّى اللهُ عَلَيْهِ وَسَلَّمَ إِذَا نَزَلَ الْوَحْيُ «بِسْمِ اللهِ الرَّحْمَنِ الرَّحِيمِ»",
            "page": "70",
            "part": "1",
            "seal": "19FA49F7"
        },
        {
            "hno": "43",
            "id": "85",
            "nass": "43 - حَدَّثَنَا إِبْرَاهِيمُ بْنُ هَاشِمٍ الْبَغَوِيُّ، حَدَّثَنَا سَعِيدُ بْنُ زُنْبُورٍ، حَدَّثَنَا عَبْدُ الْمَجِيدِ بْنُ عَبْدِ الْعَزِيزِ بْنِ أَبِي رَوَّادٍ، عَنِ ابْنِ جُرَيْجٍ، عَنْ عَمْرِو بْنِ دِينَارٍ، عَنْ سَعِيدِ بْنِ جُبَيْرٍ، عَنْ عَبْدِ اللَّهِ بْنِ عَبَّاسٍ قَالَ: \" كَانَ جِبْرِيلُ عَلَيْهِ السَّلَامُ إِذَا جَاءَ إِلَى رَسُولِ اللَّهِ صَلَّى اللهُ عَلَيْهِ وَسَلَّمَ بِالْقُرْآنِ §أَوَّلُ مَا يُلْقِي عَلَيْهِ (بِسْمِ اللَّهِ الرَّحْمَنِ الرَّحِيمِ) فَإِذَا قَالَ جِبْرِيلُ عَلَيْهِ السَّلَامُ: (بِسْمِ اللَّهِ الرَّحْمَنِ الرَّحِيمِ) الثَّانِيَةَ. عَلِمَ رَسُولُ اللَّهِ صَلَّى اللهُ عَلَيْهِ وَسَلَّمَ أَنَّهُ قَدْ خَتَمَ السُّورَةَ وَافْتَتَحَ الْأُخْرَى \"",
            "page": "70",
            "part": "1",
            "seal": "C140E791"
        },
        {
            "hno": null,
            "id": "86",
            "nass": "§بَابُ أَوَّلِ مَا أُنْزِلَ مِنَ التَّوْرَاةِ بِسْمِ اللَّهِ الرَّحْمَنِ الرَّحِيمِ",
            "page": "71",
            "part": "1",
            "seal": "A53E8375"
        },
        {
            "hno": "44",
            "id": "87",
            "nass": "44 - حَدَّثَنَا يَحْيَى بْنُ عُثْمَانَ بْنِ صَالِحٍ الْمِصْرِيُّ، حَدَّثَنَا أَبُو الْأَسْوَدِ النَّضِرُ بْنُ عَبْدِ الْجَبَّارِ، حَدَّثَنَا ابْنُ لَهِيعَةَ، عَنْ يَزِيدَ بْنِ أَبِي حَبِيبٍ، عَنْ أَبِي الْخَيْرِ مَرْثَدِ بْنِ عَبْدِ اللَّهِ الْيَزَنِيُّ، عَنْ كَعْبِ الْأَحْبَارِ رَحِمَهُ اللَّهُ قَالَ: \" §أَوَّلُ مَا أَنْزَلَ اللَّهُ عَزَّ وَجَلَّ مِنَ التَّوْرَاةِ: بِسْمِ اللَّهِ الرَّحْمَنِ الرَّحِيمِ {قُلْ تَعَالَوْا أَتْلُ مَا حَرَّمَ رَبُّكُمْ عَلَيْكُمْ} [الأنعام: 151] الْآيَاتِ \"",
            "page": "71",
            "part": "1",
            "seal": "60117B12"
        },
        {
            "hno": null,
            "id": "88",
            "nass": "§بَابُ أَوَّلِ مَنْ شَابَ",
            "page": "72",
            "part": "1",
            "seal": "B3FD6F9A"
        },
        {
            "hno": "45",
            "id": "89",
            "nass": "45 - حَدَّثَنَا هَاشِمُ بْنُ مَرْثَدٍ الطَّبَرَانِيُّ، حَدَّثَنَا مُحَمَّدُ بْنُ إِسْمَاعِيلَ بْنِ عَيَّاشٍ: \" §أَوَّلُ مَنْ شَابَ إِبْرَاهِيمُ عَلَيْهِ السَّلَامُ: أَصْبَحَ أَشْمَطَ فَقَالَ: يَا رَبِّ مَا هَذَا؟ قَالَ: وَقَارٌ قَالَ: اللَّهُمَّ زِدْنِي وَقَارًا \"",
            "page": "72",
            "part": "1",
            "seal": "B711A3B8"
        },
        {
            "hno": null,
            "id": "90",
            "nass": "§بَابُ أَوَّلِ مَا فُرِضَتِ الصَّلَاةُ",
            "page": "73",
            "part": "1",
            "seal": "6C1374E1"
        },
        {
            "hno": "46",
            "id": "91",
            "nass": "46 - حَدَّثَنَا عَلِيُّ بْنُ عَبْدِ الْعَزِيزِ، حَدَّثَنَا الْقَعْنَبِيُّ، حَدَّثَنَا عَبْدُ الْعَزِيزِ بْنُ مُحَمَّدٍ الدَّرَاوَرْدِيُّ، عَنْ سَعْدِ بْنِ سَعِيدٍ الْأَنْصَارِيِّ، عَنِ السَّائِبِ بْنِ يَزِيدَ رَضِيَ اللَّهُ عَنْهُ قَالَ: «§فُرِضَتِ الصَّلَاةُ أَوَّلَ مَا فُرِضَتْ رَكْعَتَيْنِ إِلَّا الْمَغْرِبَ فَزِيدَ فِي صَلَاةِ الْحَضَرِ فَأُقِرَّتْ صَلَاةُ السَّفَرِ عَلَى الْفَرِيضَةِ الْأُولَى»",
            "page": "73",
            "part": "1",
            "seal": "AE809985"
        },
        {
            "hno": null,
            "id": "92",
            "nass": "§بَابُ أَوَّلِ مَنْ سَنَّ الْقَتْلَ",
            "page": "74",
            "part": "1",
            "seal": "3EBC202B"
        },
        {
            "hno": "47",
            "id": "93",
            "nass": "47 - حَدَّثَنَا إِسْحَاقُ بْنُ إِبْرَاهِيمَ الدَّبَرِيُّ، عَنْ عَبْدِ الرَّزَّاقِ، عَنِ الثَّوْرِيِّ، عَنِ الْأَعْمَشِ، عَنْ عَبْدِ اللَّهِ بْنِ مُرَّةَ، عَنْ مَسْرُوقٍ، عَنْ عَبْدِ اللَّهِ بْنِ مَسْعُودٍ قَالَ: قَالَ رَسُولُ اللَّهِ صَلَّى اللهُ عَلَيْهِ وَسَلَّمَ: «§مَا مِنْ نَفْسٍ تُقْتَلُ ظُلْمًا إِلَّا كَانَ عَلَى ابْنِ آدَمَ الْقَاتِلِ كِفْلٌ مِنْهَا لِأَنَّهُ أَوَّلُ مَنْ سَنَّ الْقَتْلَ»",
            "page": "74",
            "part": "1",
            "seal": "796D6C73"
        },
        {
            "hno": null,
            "id": "94",
            "nass": "§بَابُ أَوَّلِ مَنْ عَرَفَ رَسُولَ اللهِ لَمَّا فَقَدَهُ أَصْحَابُهُ يَوْمَ أُحُدٍ",
            "page": "75",
            "part": "1",
            "seal": "F8392971"
        },
        {
            "hno": "48",
            "id": "95",
            "nass": "48 - حَدَّثَنَا مُحَمَّدُ بْنُ أَحْمَدَ بْنِ أَبِي بَكْرٍ الْمُقَدَّمِيُّ الْقَاضِي، حَدَّثَنَا عَبْدُ اللَّهِ بْنُ شَبِيبٍ الْمُزَنِيُّ، حَدَّثَنَا إِبْرَاهِيمُ بْنُ يَحْيَى بْنِ هَانِئٍ الشَّجَرِيُّ، عَنْ أَبِيهِ، عَنْ مُحَمَّدِ بْنِ إِسْحَاقَ، عَنِ ابْنِ شِهَابٍ، وَعَاصِمِ بْنِ عُمَرَ بْنِ قَتَادَةَ، عَنْ عَبْدِ اللَّهِ بْنِ كَعْبِ بْنِ مَالِكٍ، عَنْ أَبِيهِ كَعْبٍ قَالَ: «§أَنَا أَوَّلُ مَنْ عَرَفَ رَسُولَ اللَّهِ صَلَّى اللهُ عَلَيْهِ وَسَلَّمَ لَمَّا فَقَدْنَاهُ يَوْمَ أُحُدٍ عَرَفْتُهُ بِعَيْنَيْهِ مِنْ تَحْتِ الْمِغْفَرِ»",
            "page": "75",
            "part": "1",
            "seal": "8AEB44CE"
        },
        {
            "hno": null,
            "id": "96",
            "nass": "§بَابُ أَوَّلِ مَا يَكْفَأُ الدِّينَ",
            "page": "76",
            "part": "1",
            "seal": "C1AB2796"
        },
        {
            "hno": "49",
            "id": "97",
            "nass": "49 - حَدَّثَنَا عَبْدُ اللَّهِ بْنُ أَحْمَدَ بْنِ حَنْبَلٍ، حَدَّثَنِي شَيْبَانُ بْنُ فَرُّوخَ الْأُبُلِّيُّ، حَدَّثَنَا مُحَمَّدُ بْنُ رَاشِدٍ، عَنْ سُلَيْمَانَ بْنِ مُوسَى، عَنِ الْقَاسِمِ بْنِ مُحَمَّدٍ، عَنْ عَائِشَةَ رَضِيَ اللَّهُ عَنْهَا عَنِ النَّبِيِّ صَلَّى اللهُ عَلَيْهِ وَسَلَّمَ قَالَ: «§أَوَّلُ مَا يَكْفَأُ الدِّينَ كَمَا يُكْفَأُ الْإِنَاءُ شَيْءٌ تُسَمِّيهِ أُمَّتِي الْخَمْرَ وَيَسْتَحِلُّونَهَا بِهِ»",
            "page": "76",
            "part": "1",
            "seal": "BDA6A627"
        },
        {
            "hno": null,
            "id": "98",
            "nass": "§بَابُ أَوَّلِ جَدَّةٍ أَعْطَاهَا رَسُولُ اللَّهِ صَلَّى اللهُ عَلَيْهِ وَسَلَّمَ",
            "page": "77",
            "part": "1",
            "seal": "AD077BBB"
        },
        {
            "hno": "50",
            "id": "99",
            "nass": "50 - حَدَّثَنَا إِدْرِيسُ بْنُ جَعْفَرٍ الْعَطَّارُ، حَدَّثَنَا يَزِيدُ بْنُ هَارُونَ، حَدَّثَنَا مُحَمَّدُ بْنُ سَالِمٍ، عَنِ الشَّعْبِيِّ، عَنْ مَسْرُوقٍ، عَنْ عَبْدِ اللَّهِ بْنِ مَسْعُودٍ قَالَ: «§أَوَّلُ جَدَّةٍ أَعْطَاهَا رَسُولُ اللَّهِ صَلَّى اللهُ عَلَيْهِ وَسَلَّمَ السُّدُسَ»",
            "page": "77",
            "part": "1",
            "seal": "D1664B6E"
        },
        {
            "hno": null,
            "id": "100",
            "nass": "§بَابُ إِنَّ أَوَّلَ مَنْ أَسْلَمَ عَلِيُّ بْنُ أَبِي طَالِبٍ",
            "page": "78",
            "part": "1",
            "seal": "008F9211"
        },
        {
            "hno": "51",
            "id": "101",
            "nass": "51 - حَدَّثَنَا الْحَسَنُ بْنُ عَبْدِ الْأَعْلَى الْبَوْسِيُّ الصَّنْعَانِيُّ، حَدَّثَنَا عَبْدُ الرَّزَّاقِ، حَدَّثَنَا سُفْيَانُ الثَّوْرِيُّ، عَنْ سَلَمَةَ بْنِ كُهَيْلٍ، عَنْ أَبِي صَادِقٍ، عَنْ عُلَيْمٍ الْكِنْدِيِّ، عَنْ سَلْمَانَ الْفَارِسِيِّ رَضِيَ اللَّهُ عَنْهُ قَالَ: «§أَوَّلُ هَذِهِ الْأُمَّةِ وُرُودًا عَلَى نَبِيِّهَا أَوَّلُهَا إِسْلَامًا عَلِيُّ بْنُ أَبِي طَالِبٍ»",
            "page": "78",
            "part": "1",
            "seal": "239BD5C8"
        },
        {
            "hno": null,
            "id": "102",
            "nass": "§بَابُ أَوَّلِ مَنْ أَسْلَمَ",
            "page": "78",
            "part": "1",
            "seal": "D0D591A9"
        },
        {
            "hno": null,
            "id": "103",
            "nass": "حَدَّثَنَا إِسْحَاقُ بْنُ إِبْرَاهِيمَ، عَنْ عَبْدِ الرَّزَّاقِ، عَنْ مَعْمَرٍ، عَنْ عَبْدِ الْكَرِيمِ الْجَزَرِيِّ، عَنْ مِقْسَمٍ، عَنْ عَبْدِ اللَّهِ بْنِ عَبَّاسٍ قَالَ: «§أَوَّلُ مَنْ أَسْلَمَ عَلِيٌّ رَضِيَ اللَّهُ عَنْهُ»",
            "page": "78",
            "part": "1",
            "seal": "17298372"
        },
        {
            "hno": null,
            "id": "104",
            "nass": "§بَابُ أَوَّلِ مَنْ أَسْلَمَ",
            "page": "78",
            "part": "1",
            "seal": "EC97CF79"
        },
        {
            "hno": "53",
            "id": "105",
            "nass": "53 - حَدَّثَنَا أَبُو يَزِيدَ الْقَرَاطِيسِيُّ، حَدَّثَنَا أَسَدُ بْنُ مُوسَى، حَدَّثَنَا شُعْبَةُ، عَنْ عَمْرِو بْنِ مُرَّةَ، عَنْ أَبِي حَمْزَةَ الْأَنْصَارِيِّ، عَنْ زَيْدِ بْنِ أَرْقَمَ، قَالَ: «§أَوَّلُ مَنْ أَسْلَمَ عَلِيُّ بْنُ أَبِي طَالِبٍ رَضِيَ اللَّهُ عَنْهُ»",
            "page": "79",
            "part": "1",
            "seal": "4D6EF33C"
        },
        {
            "hno": null,
            "id": "106",
            "nass": "§بَابُ مَنْ قَالَ خَدِيجَةُ ثُمَّ عَلِيٌّ رَضِيَ اللَّهُ عَنْهُمَا",
            "page": "80",
            "part": "1",
            "seal": "78FDD077"
        },
        {
            "hno": "54",
            "id": "107",
            "nass": "54 - حَدَّثَنَا الْعَبَّاسُ بْنُ الْفَضْلِ الْأَسْفَاطِيُّ، حَدَّثَنَا عَبْدُ الْعَزِيزِ بْنُ الْخَطَّابِ، حَدَّثَنَا عَلِيُّ بْنُ غُرَابٍ، عَنْ يُوسُفَ بْنِ صُهَيْبٍ، عَنْ أَبِي بُرْدَةَ، عَنْ أَبِيهِ، قَالَ: «§خَدِيجَةُ أَوَّلُ مَنْ أَسْلَمَ مَعَ رَسُولِ اللَّهِ ثُمَّ عَلِيُّ»",
            "page": "80",
            "part": "1",
            "seal": "4BAABDB2"
        },
        {
            "hno": null,
            "id": "108",
            "nass": "§بَابُ مَنْ قَالَ أَوَّلُ مَنْ أَسْلَمَ أَبُو بَكْرٍ رَضِيَ اللَّهُ عَنْهُ",
            "page": "81",
            "part": "1",
            "seal": "617806D3"
        },
        {
            "hno": "55",
            "id": "109",
            "nass": "55 - حَدَّثَنَا عَبْدَانُ بْنُ أَحْمَدَ، حَدَّثَنَا الْجَرَّاحُ بْنُ مَخْلَدٍ، حَدَّثَنَا النَّضِرُ بْنُ حَمَّادٍ، حَدَّثَنَا سَيْفُ بْنُ عُمَرَ، عَنْ مُوسَى بْنِ عُقْبَةَ، عَنْ نَافِعٍ، عَنِ ابْنِ عُمَرَ رَضِيَ اللَّهُ عَنْهُمَا قَالَ: «§أَوَّلِ مَنْ أَسْلَمَ أَبُو بَكْرٍ رَضِيَ اللَّهُ عَنْهُ»",
            "page": "81",
            "part": "1",
            "seal": "B842BD38"
        },
        {
            "hno": null,
            "id": "110",
            "nass": "§بَابُ أَوَّلِ خَبَرٍ جَاءَ الْمَدِينَةَ بِمَبْعَثِ رَسُولِ اللهِ صَلَّى اللهُ عَلَيْهِ وَسَلَّمَ",
            "page": "83",
            "part": "1",
            "seal": "8DEC991E"
        },
        {
            "hno": "56",
            "id": "111",
            "nass": "56 - حَدَّثَنَا أَبُو أَيُّوبَ أَحْمَدُ بْنُ بَشِيرٍ الطَّيَالِسِيُّ، حَدَّثَنَا عَبْدُ الْجَبَّارِ بْنُ عَاصِمٍ، حَدَّثَنَا أَبُو الْمَلِيحِ الرَّقِّيُّ الْحَسَنُ بْنُ عَمْرٍو، عَنْ عَبْدِ اللَّهِ بْنِ مُحَمَّدِ بْنِ عَقِيلٍ، عَنْ جَابِرِ بْنِ عَبْدِ اللَّهِ، رَضِيَ اللَّهُ عَنْهُمَا قَالَ: \" §أَوَّلُ خَبَرٍ جَاءَ إِلَى الْمَدِينَةِ بِمَبْعَثِ رَسُولِ اللَّهِ صَلَّى اللهُ عَلَيْهِ وَسَلَّمَ حِينَ بُعِثَ أَنَّ امْرَأَةً مِنْ أَهْلِ الْمَدِينَةِ كَانَ لَهَا تَابِعٌ مِنَ الْجِنِّ جَاءَ فِي صُورَةِ طَيْرٍ حَتَّى وَقَعَ عَلَى جِذْعٍ لَهُمْ فَقَالَتْ لَهُ: أَلَا تَنْزِلُ إِلَيْنَا فَتُحَدِّثَنَا بِحَدِيثِكَ وَتُخْبِرَنَا بِخَبَرِكَ فَقَالَ: لَا , إِنَّهُ قَدْ بُعِثَ نَبِيُّ بِمَكَّةَ حَرَّمَ الزِّنَا وَمُنِعَ مِنَّا الْفِرَارُ \"",
            "page": "83",
            "part": "1",
            "seal": "5A8E4F40"
        },
        {
            "hno": null,
            "id": "112",
            "nass": "§بَابُ أَوَّلِ أَهْلِ رَسُولِ اللَّهِ كَانَ أَسْرَعَ بِهِ لُحُوقًا",
            "page": "84",
            "part": "1",
            "seal": "5EF21B30"
        },
        {
            "hno": "57",
            "id": "113",
            "nass": "57 - حَدَّثَنَا عَلِيُّ بْنُ عَبْدِ الْعَزِيزِ، حَدَّثَنَا أَبُو نُعَيْمٍ، حَدَّثَنَا زَكَرِيَّا بْنُ أَبِي زَائِدَةَ، عَنْ فِرَاسِ بْنِ يَحْيَى، عَنِ الشَّعْبِيِّ، عَنْ مَسْرُوقٍ، عَنْ عَائِشَةَ قَالَتْ: \" أَقْبَلَتْ فَاطِمَةُ رَضِيَ اللَّهُ عَنْهَا تَمْشِي كَأَنَّ مِشْيَتَهَا مِشْيَةُ رَسُولِ اللَّهِ صَلَّى اللهُ عَلَيْهِ وَسَلَّمَ فَقَالَ: مَرْحَبًا بِابْنَتِي فَأَجْلَسَهَا عَنْ يَمِينِهِ فَأَسَرَّ إِلَيْهَا حَدِيثًا فَبَكَتْ فَقُلْتُ لَهَا اسْتَحَضَّكِ رَسُولُ اللَّهِ صَلَّى اللهُ عَلَيْهِ وَسَلَّمَ بِحَدِيثِهِ ثُمَّ تَبْكِينَ ثُمَّ أَسَرَّ إِلَيْهَا حَدِيثًا فَضَحِكَتْ. فَقُلْتُ: مَا رَأَيْتُ كَالْيَوْمِ فَرَحًا أَقْرَبَ مِنْ حُزْنٍ فَسَأَلْتُهَا عَمَّا قَالَ. فَقَالَتْ: مَا كُنْتُ لِأُفْشِيَ سِرَّ رَسُولِ اللَّهِ صَلَّى اللهُ عَلَيْهِ وَسَلَّمَ حَتَّى إِذَا قُبِضَ رَسُولُ اللَّهِ صَلَّى اللهُ عَلَيْهِ وَسَلَّمَ سَأَلْتُهَا فَقَالَتْ: إِنَّهُ أَسَرَّ إِلَيَّ فَقَالَ: إِنَّ جِبْرِيلَ عَلَيْهِ السَّلَامُ كَانَ يُعَارِضُنِي بِالْقُرْآنِ كُلَّ سَنَةٍ مَرَّةً وَإِنَّهُ عَارَضَنِي الْعَامَ مَرَّتَيْنِ وَلَا أَرَاهُ إِلَّا قَدْ حَضَرَ أَجَلِي §وَإِنَّكِ أَوَّلُ أَهْلِ بَيْتِي لِحَاقًا بِي وَنِعْمَ السَّلَفُ أَنَا لَكِ فَبَكَيْتُ لِذَلِكَ ثُمَّ قَالَ: أَلَا تَرْضَيْنَ أَنْ تَكُونِي سَيِّدَةَ نِسَاءِ هَذِهِ الْأُمَّةِ أَوْ نِسَاءِ الْمُؤْمِنِينَ فَضَحِكْتُ لِذَلِكَ \"",
            "page": "84",
            "part": "1",
            "seal": "F1B4D462"
        },
        {
            "hno": null,
            "id": "114",
            "nass": "§بَابُ أَوَّلِ النَّاسِ هَلَاكًا",
            "page": "86",
            "part": "1",
            "seal": "AB650444"
        },
        {
            "hno": "58",
            "id": "115",
            "nass": "58 - حَدَّثَنَا زَكَرِيَّا السَّاجِيُّ، حَدَّثَنَا سَلْمُ بْنُ جُنَادَةَ، حَدَّثَنَا أَحْمَدُ بْنُ بَشِيرٍ الْهَمَذَانِيُّ، عَنْ مُجَالِدٍ، عَنِ الشَّعْبِيِّ، عَنْ مَسْرُوقٍ، عَنْ عَائِشَةَ، قَالَتْ: قَالَ رَسُولُ اللَّهِ صَلَّى اللهُ عَلَيْهِ وَسَلَّمَ: «§أَوَّلُ النَّاسِ هَلَاكًا قَوْمُكِ» قَالَتْ: قُلْتُ: يَا رَسُولَ اللَّهِ كَيْفَ؟ قَالَ: «يَسْتَحْلِيهِمُ الْمَوْتُ وَيَتَنَافَسُ فِيهِمْ» قُلْتُ: فَمَا بَقَاءُ النَّاسِ بَعْدَهُمْ قَالَ: «بَقَاءُ الْحِمَارِ إِذَا كُسِرَ صُلْبُهُ»",
            "page": "86",
            "part": "1",
            "seal": "77154088"
        },
        {
            "hno": null,
            "id": "116",
            "nass": "§بَابُ أَوَّلِ حَبْسٍ كَانَ فِي الْإِسْلَامِ",
            "page": "87",
            "part": "1",
            "seal": "69831816"
        },
        {
            "hno": "59",
            "id": "117",
            "nass": "59 - حَدَّثَنَا مُحَمَّدُ بْنُ عَبْدوسِ بْنِ كَامِلٍ السَّرَّاجُ، حَدَّثَنَا مُحَمَّدُ بْنُ يَزِيدَ الْأَدَمِيُّ، حَدَّثَنَا يَحْيَى بْنُ سُلَيْمٍ الطَّائِفِيُّ، عَنْ عُبَيْدِ اللَّهِ بْنِ عُمَرَ، عَنْ نَافِعٍ، عَنِ ابْنِ عُمَرَ، أَنَّ عُمَرَ، اسْتَشَارَ النَّبِيَّ صَلَّى اللهُ عَلَيْهِ وَسَلَّمَ فِي صَدَقَةِ أَرْضِهِ فَقَالَ رَسُولُ اللَّهِ صَلَّى اللهُ عَلَيْهِ وَسَلَّمَ: «§احْبِسْ أَصْلَهَا وَتَصَدَّقْ بِثَمَرَتِهَا» . قَالَ ابْنُ عُمَرَ: فَإِنَّهَا لَأَوَّلُ صَدَقَةٍ تُصُدِّقَ بِهَا فِي الْإِسْلَامِ يَعْنِي أَوَّلَ حَبْسٍ",
            "page": "87",
            "part": "1",
            "seal": "F833AEC4"
        },
        {
            "hno": null,
            "id": "118",
            "nass": "§بَابُ أَوَّلِ مَنْ أَسْلَمَ مِنَ الْعَرَبِ بَعْدَ الْأَنْصَارِ",
            "page": "88",
            "part": "1",
            "seal": "6AF977C3"
        },
        {
            "hno": "60",
            "id": "119",
            "nass": "60 - حَدَّثَنَا عَبْدُ اللَّهِ بْنُ نَاجِيَةَ الْبَغْدَادِيُّ، حَدَّثَنَا عَبْدُ اللَّهِ بْنُ شَبِيبٍ الْمُزَنِيُّ، حَدَّثَنَا إِسْمَاعِيلُ بْنُ أَبِي أُوَيْسٍ، حَدَّثَنِي أَبِي، عَنْ زَيْدِ بْنِ أَسْلَمَ، عَنْ أَبِيهِ، عَنْ عُمَرَ، رَضِيَ اللَّهُ عَنْهُ قَالَ: «كَانَ §أَهْلُ الْيَمَنِ أَوَّلَ مَنْ أَسْلَمَ مِنَ الْعَرَبِ بَعْدَ الْأَنْصَارِ ثُمَّ عَبْدُ الْقَيْسِ أَهْلُ الْبَحْرَيْنِ»",
            "page": "88",
            "part": "1",
            "seal": "FADDB390"
        },
        {
            "hno": null,
            "id": "120",
            "nass": "§بَابُ أَيُّ الْمَدِينَتَيْنِ يُفْتَحُ أَوَّلًا قُسْطَنْطِينِيَّةُ أَوْ رُومِيَّةُ",
            "page": "89",
            "part": "1",
            "seal": "19549EAA"
        },
        {
            "hno": "61",
            "id": "121",
            "nass": "61 - حَدَّثَنَا عَبْدُ اللَّهِ بْنُ الْحُسَيْنِ الْمِصِّيصِيُّ، حَدَّثَنَا يَحْيَى بْنُ إِسْحَاقَ السَّيْلَحِينِيُّ، حَدَّثَنَا يَحْيَى بْنُ أَيُّوبَ، عَنْ أَبِي قَبِيلٍ، عَنْ عَبْدِ اللَّهِ بْنِ عَمْرٍو، قَالَ: بَيْنَمَا نَحْنُ عِنْدَ رَسُولِ اللَّهِ صَلَّى اللهُ عَلَيْهِ وَسَلَّمَ إِذْ سُئِلَ أَيُّ الْمَدِينَتَيْنِ تُفْتَحُ أَوَّلُ: قُسْطَنْطِينِيَّةُ أَوْ رُومِيَّةُ؟ فَقَالَ رَسُولُ اللَّهِ صَلَّى اللهُ عَلَيْهِ وَسَلَّمَ: «بَلْ §مَدِينَةُ هِرَقْلَ تُفْتَحُ» ، يَعْنِي قُسْطَنْطِينِيَّةَ",
            "page": "89",
            "part": "1",
            "seal": "8B633D15"
        },
        {
            "hno": null,
            "id": "122",
            "nass": "§بَابُ أَوَّلِ أَمِيرٍ أُمِّرَ فِي الْإِسْلَامِ",
            "page": "90",
            "part": "1",
            "seal": "5B1DB04A"
        },
        {
            "hno": "62",
            "id": "123",
            "nass": "62 - حَدَّثَنَا عُبَيْدُ بْنُ غَنَّامٍ، حَدَّثَنَا أَبُو بَكْرِ بْنُ أَبِي شَيْبَةَ، حَدَّثَنَا أَبُو أُسَامَةَ، عَنْ مُجَالِدٍ، عَنْ زِيَادِ بْنِ عِلَاقَةَ، عَنْ سَعْدِ بْنِ أَبِي وَقَّاصٍ، رَضِيَ اللَّهُ عَنْهُ قَالَ «أَمَّرَ رَسُولُ اللَّهِ صَلَّى اللهُ عَلَيْهِ وَسَلَّمَ عَبْدَ اللَّهِ بْنَ جَحْشِ بْنِ رِئَابٍ عَلَى سَرِيَّةٍ وَكَانَ §أَوَّلَ أَمِيرٍ فِي الْإِسْلَامِ»",
            "page": "90",
            "part": "1",
            "seal": "EB7C5AB0"
        },
        {
            "hno": null,
            "id": "124",
            "nass": "§بَابُ أَوَّلِ مَنْ فَاءَ مِنْ أَصْحَابِ رَسُولِ اللَّهِ صَلَّى اللهُ عَلَيْهِ وَسَلَّمَ بَعْدَ الْهَزِيمَةِ يَوْمَ أُحُدٍ",
            "page": "91",
            "part": "1",
            "seal": "D80C34A1"
        },
        {
            "hno": "63",
            "id": "125",
            "nass": "63 - حَدَّثَنَا أَحْمَدُ بْنُ يَحْيَى الْحُلْوَانِيُّ، حَدَّثَنَا سَعِيدُ بْنُ سُلَيْمَانَ الْوَاسِطِيُّ، حَدَّثَنَا إِسْحَاقُ بْنُ يَحْيَى بْنِ طَلْحَةَ بْنِ عُبَيْدِ اللَّهِ، حَدَّثَنَا عَمِّي عِيسَى بْنُ طَلْحَةَ، عَنْ عَائِشَةَ، رَضِيَ اللَّهُ عَنْهَا قَالَتْ: قَالَ أَبُو بَكْرٍ الصِّدِّيقُ رَضِيَ اللَّهُ عَنْهُ: وَكُنْتُ §أَوَّلَ مَنْ فَاءَ إِلَى رَسُولِ اللَّهِ صَلَّى اللهُ عَلَيْهِ وَسَلَّمَ يَوْمَ أُحُدٍ وَمَعَهُ طَلْحَةُ فَوَجَدْنَاهُ قَدْ غَلَبَهُ النَّزْفُ وَأَدْنَى رَسُولُ اللَّهِ صَلَّى اللهُ عَلَيْهِ وَسَلَّمَ أَمْثَلَ مِنْهُ فَقَالَ رَسُولُ اللَّهِ صَلَّى اللهُ عَلَيْهِ وَسَلَّمَ: «عَلَيْكُمْ بِصَاحِبِكُمْ» فَلَمْ نُقْبِلْ عَلَيْهِ وَأَقْبَلْنَا عَلَى رَسُولِ اللَّهِ صَلَّى اللهُ عَلَيْهِ وَسَلَّمَ وَعَلَى رَأْسِهِ مِغْفَرٌ قَدْ عَلِقَ بِوَجْنَتَيْهِ وَبَيْنِي وَبَيْنَ الْمُشْرِكِينَ رَجُلٌ وَأَنَا أَقْرَبُ إِلَى رَسُولِ اللَّهِ صَلَّى اللهُ عَلَيْهِ وَسَلَّمَ فَإِذَا هُوَ أَبُوعُبَيْدَةَ بْنُ الْجَرَّاحِ. فَذَهَبْتُ لِأَنْزِعَهُ عَنْهُ فَقَالَ أَبُوعُبَيْدَةَ: أَنْشُدُكَ اللَّهَ يَا أَبَا بَكْرٍ إِلَّا تَرَكْتَنِي أَنْزِعُهُ. فَجَذَبَهَا فَأَخْرَجَهَا فَانْتُزِعَتْ ثَنِيَّةُ أَبِي عُبَيْدَةَ فَذَهَبْتُ لِأَنْزِعَ الْحَلْقَةَ الْأُخْرَى فَقَالَ أَبُوعُبَيْدَةَ: أَنْشُدُكَ اللَّهَ يَا أَبَا بَكْرٍ إِلَّا تَرَكْتَنِي أَنْزِعُهُ فَتَرَكْتُهُ فَانْتَزَعَهُ فَانْتُزِعَتْ ثَنِيَّةُ أَبِي عُبَيْدَةَ الْأُخْرَى فَقَالَ رَسُولُ اللَّهِ صَلَّى اللهُ عَلَيْهِ وَسَلَّمَ: «إِنَّ صَاحِبَكُمْ قَدِ اسْتَوْجَبَ»",
            "page": "91",
            "part": "1",
            "seal": "407A6371"
        },
        {
            "hno": null,
            "id": "126",
            "nass": "§بَابُ أَوَّلِ مَا ظَهَرَ مِنْ إِيمَانِ النَّجَاشِيِّ رَحِمَهُ اللَّهُ",
            "page": "93",
            "part": "1",
            "seal": "8BD122F9"
        },
        {
            "hno": "64",
            "id": "127",
            "nass": "64 - حَدَّثَنَا مُحَمَّدُ بْنُ عَلِيِّ بْنِ الْأَحْمَرِ النَّاقِدُ الْبَصْرِيُّ، حَدَّثَنَا مُحَمَّدُ بْنُ يَحْيَى الْقُطَعِيُّ، حَدَّثَنَا وَهْبُ بْنُ جَرِيرِ بْنِ حَازِمٍ، حَدَّثَنِي أَبِي، عَنْ مُحَمَّدِ بْنِ إِسْحَاقَ، عَنِ الزُّهْرِيِّ، عَنْ عَائِشَةَ قَالَتْ: «كَانَ §أَوَّلَ مَا ظَهَرَ مِنْ إِيمَانِ النَّجَاشِيِّ عَدْلُهُ وَصَلَابَتُهُ فِي دِينِهِ»",
            "page": "93",
            "part": "1",
            "seal": "0D41537B"
        },
        {
            "hno": null,
            "id": "128",
            "nass": "§بَابُ أَوَّلِ مَنْ يَسْمَعُ نَفْخَةَ الصُّورِ يَوْمَ الْقِيَامَةِ",
            "page": "94",
            "part": "1",
            "seal": "807863B2"
        },
        {
            "hno": "65",
            "id": "129",
            "nass": "65 - حَدَّثَنَا عَبْدُ اللَّهِ بْنُ أَحْمَدَ بْنِ حَنْبَلٍ، حَدَّثَنِي يَحْيَى بْنُ مَعِينٍ، حَدَّثَنَا مُحَمَّدُ بْنُ جَعْفَرٍ غُنْدَرٌ، حَدَّثَنَا شُعْبَةُ، عَنِ النُّعْمَانِ بْنِ سَالِمٍ، عَنْ يَعْقُوبَ بْنِ عَاصِمٍ، عَنْ عُرْوَةَ بْنِ مَسْعُودٍ الثَّقَفِيِّ، عَنْ عَبْدِ اللَّهِ بْنِ عُمَرَ، رَضِيَ اللَّهُ عَنْهُمَا قَالَ: قَالَ رَسُولُ اللَّهِ صَلَّى اللهُ عَلَيْهِ وَسَلَّمَ: «§يُنْفَخُ فِي الصُّورِ فَلَا يَسْمَعُهُ أَحَدٌ إِلَّا أَصْغَى إِلَيْهِ وَأَوَّلُ مَنْ يَسْمَعُهُ رَجُلٌ يَلُوطُ حَوْضَهُ فَيُصْعَقُ»",
            "page": "94",
            "part": "1",
            "seal": "112C8753"
        },
        {
            "hno": null,
            "id": "130",
            "nass": "§بَابُ أَوَّلِ مَا يَقُولُ اللَّهُ لِلْمُؤْمِنِينَ يَوْمَ الْقِيَامَةِ",
            "page": "95",
            "part": "1",
            "seal": "4F5E0BCF"
        },
        {
            "hno": "66",
            "id": "131",
            "nass": "66 - حَدَّثَنَا عَبْدُ اللَّهِ بْنُ أَحْمَدَ بْنِ حَنْبَلٍ، حَدَّثَنِي الْعَبَّاسُ بْنُ الْوَلِيدِ، حَدَّثَنَا ابْنُ الْمُبَارَكِ، عَنْ يَحْيَى بْنِ أَيُّوبَ، عَنْ عُبَيْدِ اللَّهِ بْنِ زَحْرٍ، عَنْ خَالِدِ بْنِ أَبِي عِمْرَانَ، عَنْ أَبِي عَيَّاشٍ، عَنْ مُعَاذِ بْنِ جَبَلٍ، رَضِيَ اللَّهُ عَنْهُ قَالَ: قَالَ رَسُولُ اللَّهِ صَلَّى اللهُ عَلَيْهِ وَسَلَّمَ: \" إِنْ شِئْتُمْ أَنْبَأْتُكُمْ بِمَا يَقُولُ اللَّهُ لِلْمُؤْمِنِينَ يَوْمَ الْقِيَامَةِ. قَالُوا: نَعَمْ. قَالَ: يَقُولُ: §هَلْ أَحْبَبْتُمْ لِقَائِي؟ فَيَقُولُونَ: نَعَمْ رَبَّنَا. فَيَقُولُ: لِمَ؟ فَيَقُولُونَ: رَجَوْنَا عَفْوَكَ وَمَغْفِرَتَكَ. فَيَقُولُ: قَدْ وَجَبَتْ لَكُمْ مَغْفِرَتِي \"",
            "page": "95",
            "part": "1",
            "seal": "E8982DEE"
        },
        {
            "hno": null,
            "id": "132",
            "nass": "§بَابُ أَوَّلِ مَنْ يُجِيزُ عَلَى الصِّرَاطِ يَوْمَ الْقِيَامَةِ",
            "page": "96",
            "part": "1",
            "seal": "7365272E"
        },
        {
            "hno": "67",
            "id": "133",
            "nass": "67 - حَدَّثَنَا الدَّبَرِيُّ، عَنْ عَبْدِ الرَّزَّاقِ، عَنْ مَعْمَرٍ، عَنِ الزُّهْرِيِّ، عَنْ عَطَاءِ بْنِ يَزِيدَ، عَنْ أَبِي هُرَيْرَةَ قَالَ: قَالَ رَسُولُ اللَّهِ صَلَّى اللهُ عَلَيْهِ وَسَلَّمَ: «§أَنَا أَوَّلُ مَنْ يُجِيزُ عَلَى الصِّرَاطِ يَوْمَ الْقِيَامَةِ»",
            "page": "96",
            "part": "1",
            "seal": "4BF035A4"
        },
        {
            "hno": null,
            "id": "134",
            "nass": "§بَابُ أَوَّلِ مَا تَفَوَّهَ بِهِ النَّبِيُّ فِي حُجَّةِ الْوَدَاعِ",
            "page": "97",
            "part": "1",
            "seal": "952EF21E"
        },
        {
            "hno": "68",
            "id": "135",
            "nass": "68 - حَدَّثَنَا هَاشِمُ بْنُ مَرْثَدٍ الطَّبَرَانِيُّ، حَدَّثَنَا مُحَمَّدُ بْنُ إِسْمَاعِيلَ بْنِ عَيَّاشٍ، حَدَّثَنِي أَبِي، عَنْ ضَمْضَمِ بْنِ زُرْعَةَ، عَنْ خِدَاشٍ، عَنْ أَبِي أُمَامَةَ الْبَاهِلِيِّ رَضِيَ اللَّهُ عَنْهُ قَالَ: خَطَبَ النَّبِيُّ صَلَّى اللهُ عَلَيْهِ وَسَلَّمَ فِي حُجَّةِ الْوَدَاعِ فَكَانَ أَوَّلُ مَا تَفَوَّهَ بِهِ أَنْ قَالَ: «§إِنَّ اللَّهَ يُوصِيكُمْ بِأُمَّهَاتِكُمْ إِنَّ اللَّهَ يُوصِيكُمْ بِآبَائِكُمْ إِنَّ اللَّهَ يُوصِيكُمْ بِالْأَقْرَبِ فَالْأَقْرَبِ»",
            "page": "97",
            "part": "1",
            "seal": "7DF2AB3E"
        },
        {
            "hno": null,
            "id": "136",
            "nass": "§بَابُ أَوَّلِ مَوْلُودٍ وُلِدَ فِي الْإِسْلَامِ بِالْمَدِينَةِ",
            "page": "98",
            "part": "1",
            "seal": "334593E4"
        },
        {
            "hno": "69",
            "id": "137",
            "nass": "69 - حَدَّثَنِي مَسْعَدَةُ بْنُ سَعْدٍ الْعَطَّارُ، حَدَّثَنَا إِبْرَاهِيمُ بْنُ الْمُنْذِرِ، حَدَّثَنَا عَبْدُ اللَّهِ بْنُ مُحَمَّدِ بْنِ يَحْيَى بْنِ عُرْوَةَ، عَنْ هِشَامِ بْنِ عُرْوَةَ، عَنْ أَبِيهِ، عَنْ عَائِشَةَ قَالَتْ: «§أَوَّلُ مَوْلُودٍ وُلِدَ فِي الْإِسْلَامِ بَعْدَ الْهِجْرَةِ عَبْدُ اللَّهِ بْنُ الزُّبَيْرِ»",
            "page": "98",
            "part": "1",
            "seal": "8C2720BE"
        },
        {
            "hno": null,
            "id": "138",
            "nass": "§بَابُ أَوَّلِ مَوْلُودٍ صَغِيرٍ دَخَلَ بَطْنَهُ رِيقُ النَّبِيِّ صَلَّى اللهُ عَلَيْهِ وَسَلَّمَ",
            "page": "99",
            "part": "1",
            "seal": "EF713DDC"
        },
        {
            "hno": "70",
            "id": "139",
            "nass": "70 - حَدَّثَنَا عُبَيْدُ بْنُ غَنَّامٍ، حَدَّثَنَا أَبُو بَكْرِ بْنُ أَبِي شَيْبَةَ، حَدَّثَنَا خَالِدُ بْنُ مَخْلَدٍ، عَنْ عَلِيِّ بْنِ مُسْهِرٍ، عَنْ هِشَامِ بْنِ عُرْوَةَ، عَنْ أَبِيهِ، عَنْ أَسْمَاءَ بِنْتِ أَبِي بَكْرٍ، رَضِيَ اللَّهُ عَنْهُمَا: «أَنَّهَا أَتَتِ النَّبِيَّ صَلَّى اللهُ عَلَيْهِ وَسَلَّمَ بِعَبْدِ اللَّهِ بْنِ الزُّبَيْرِ حِينَ وَضَعَتْهُ §فَطَلَبُوا تَمْرَةً يُحَنِّكُهُ بِهَا حَتَّى وَجَدُوهَا فَحَنَّكَهُ فَكَانَ أَوَّلَ شَيْءٍ دَخَلَ بَطْنَهُ رِيقُ رَسُولِ اللَّهِ صَلَّى اللهُ عَلَيْهِ وَسَلَّمَ»",
            "page": "99",
            "part": "1",
            "seal": "171F9E69"
        },
        {
            "hno": null,
            "id": "140",
            "nass": "§بَابُ أَوَّلِ مَنْ أُصِيبَ مِنَ الْأَنْصَارِ يَوْمَ بَدْرٍ",
            "page": "100",
            "part": "1",
            "seal": "046035F9"
        },
        {
            "hno": "71",
            "id": "141",
            "nass": "71 - حَدَّثَنَا إِبْرَاهِيمُ بْنُ هَاشِمٍ الْبَغَوِيُّ، حَدَّثَنَا مُحَمَّدُ بْنُ أَبِي بَكْرٍ الْمُقَدَّمِيُّ، حَدَّثَنَا مُعْتَمِرُ بْنُ سُلَيْمَانَ، عَنْ حُمَيْدٍ، عَنْ أَنَسٍ: «أَنَّ حَارِثَةَ بْنَ النُّعْمَانِ الْأَنْصَارِيِّ، كَانَ §أَوَّلَ مَنْ أُصِيبَ مِنَ الْأَنْصَارِ يَوْمَ بَدْرٍ»",
            "page": "100",
            "part": "1",
            "seal": "441665DA"
        },
        {
            "hno": null,
            "id": "142",
            "nass": "§بَابُ أَوَّلِ مَنْ ذَهَبَ عَنْهُ النُّعَاسُ يَوْمَ بَدْرٍ",
            "page": "101",
            "part": "1",
            "seal": "DFC8A4CF"
        },
        {
            "hno": "72",
            "id": "143",
            "nass": "72 - حَدَّثَنَا إِبْرَاهِيمُ بْنُ دُحَيْمٍ الدِّمَشْقِيُّ، حَدَّثَنَا أَبِي، حَدَّثَنَا الْوَلِيدُ بْنُ مُسْلِمٍ، حَدَّثَنَا ابْنُ لَهِيعَةَ، عَنْ أَبِي الْأَسْوَدِ، عَنْ عُرْوَةَ، عَنْ أَبِيهِ، قَالَ: «لَمَّا الْتَقَيْنَا يَوْمَ بَدْرٍ، كَانَ §أَوَّلُ مَنِ اسْتُقِيلَ مِنَ النَّعْسَةِ رَسُولَ اللهِ صَلَّى اللهُ عَلَيْهِ وَسَلَّمَ»",
            "page": "101",
            "part": "1",
            "seal": "35BBB7DA"
        },
        {
            "hno": null,
            "id": "144",
            "nass": "§بَابُ أَوَّلِ مَنْ طُعِنَ يَوْمَ بِئْرِ مَعُونَةَ",
            "page": "102",
            "part": "1",
            "seal": "A3D87065"
        },
        {
            "hno": "73",
            "id": "145",
            "nass": "73 - حَدَّثَنَا مُحَمَّدُ بْنُ مُحَمَّدٍ الْجُذُوعِيُّ الْقَاضِي، حَدَّثَنَا مُحَمَّدُ بْنُ مَرْزُوقٍ، حَدَّثَنَا مُحَمَّدُ بْنُ عَبْدِ اللَّهِ الْأَنْصَارِيُّ، حَدَّثَنِي أَبِي، عَنْ ثُمَامَةَ بْنِ عَبْدِ اللَّهِ بْنِ أَنَسٍ، عَنْ أَنَسٍ، قَالَ: \" بَعَثَ رَسُولُ اللَّهِ صَلَّى اللهُ عَلَيْهِ وَسَلَّمَ بِسَرِيَّةٍ إِلَى بِئْرِ مَعُونَةَ فَاسْتَعْدَى عَلَيْهِمْ عَامِرُ بْنُ الطُّفَيْلِ أُنَاسًا مِنْ بَنِي سُلَيْمٍ فَكَانَ §أَوَّلَ مَنْ طُعِنَ: حَرَامُ بْنُ مِلْحَانَ، فَتَلَقَّى دَمَهَا بِيَدِهِ وَجَعَلَ يَنْضَحُهَا عَلَى وَجْهِهِ وَيَقُولُ: فُزْتُ وَرَبِّ الْكَعْبَةِ \"",
            "page": "102",
            "part": "1",
            "seal": "BACCA9EA"
        },
        {
            "hno": null,
            "id": "146",
            "nass": "§بَابُ أَيْنَ كَانَتْ أَوَّلُ شَكْوَى رَسُولِ اللَّهِ الْأَخِيرَةِ",
            "page": "103",
            "part": "1",
            "seal": "F14C64AB"
        },
        {
            "hno": "74",
            "id": "147",
            "nass": "74 - حَدَّثَنَا إِسْحَاقُ بْنُ إِبْرَاهِيمَ الدَّبَرِيُّ، عَنْ عَبْدِ الرَّزَّاقِ، عَنْ مَعْمَرٍ، عَنِ الزُّهْرِيِّ، عَنْ أَبِي بَكْرِ بْنِ عَبْدِ الرَّحْمَنِ بْنِ الْحَارِثِ بْنِ هِشَامٍ، عَنْ أَسْمَاءَ بِنْتِ عُمَيْسٍ، رَضِيَ اللَّهُ عَنْهَا قَالَتْ: «§أَوَّلُ مَا اشْتَكَى رَسُولُ اللَّهِ فِي بَيْتِ أُمِّ سَلَمَةَ ثُمَّ حُوِّلَ إِلَى بَيْتِ عَائِشَةَ»",
            "page": "103",
            "part": "1",
            "seal": "B8DF66B8"
        },
        {
            "hno": null,
            "id": "148",
            "nass": "§بَابُ أَيُّ مَسْجِدٍ وُضِعَ فِي الْأَرْضِ أَوَّلُ",
            "page": "104",
            "part": "1",
            "seal": "C741C5D2"
        },
        {
            "hno": "75",
            "id": "149",
            "nass": "75 - حَدَّثَنَا الدَّبَرِيُّ، عَنْ عَبْدِ الرَّزَّاقِ، عَنِ الثَّوْرِيِّ، عَنِ الْأَعْمَشِ، عَنْ إِبْرَاهِيمَ التَّيْمِيِّ، عَنْ أَبِيهِ، عَنْ أَبِي ذَرٍّ، رَضِيَ اللهُ عَنْهُ قَالَ: \" قُلْتُ يَا رَسُولَ اللَّهِ §أَيُّ مَسْجِدٍ وُضِعَ فِي الْأَرْضِ أَوَّلُ؟ قَالَ: الْمَسْجِدُ الْحَرَامُ. قَالَ: قُلْتُ: ثُمَّ أَيُّ؟ قَالَ: ثُمَّ الْمَسْجِدُ الْأَقْصَى. قُلْتُ: كَمْ بَيْنَهُمَا؟ قَالَ: أَرْبَعُونَ سَنَةً \"",
            "page": "104",
            "part": "1",
            "seal": "8885DBF9"
        },
        {
            "hno": null,
            "id": "150",
            "nass": "§بَابُ أَوَّلِ مَنْ يَشْفَعُ لَهُ رَسُولُ اللَّهِ صَلَّى اللهُ عَلَيْهِ وَسَلَّمَ مِنْ أُمَّتِهِ",
            "page": "105",
            "part": "1",
            "seal": "6F0D0E12"
        },
        {
            "hno": "76",
            "id": "151",
            "nass": "76 - حَدَّثَنَا الْعَبَّاسُ بْنُ الْفَضْلِ الْأَسْفَاطِيُّ، حَدَّثَنَا إِبْرَاهِيمُ بْنُ مُحَمَّدِ بْنِ عَرْعَرَةَ، حَدَّثَنَا حَرَمِيُّ بْنُ عُمَارَةَ، حَدَّثَنِي سَعِيدُ بْنُ السَّائِبِ الطَّائِفِيُّ، عَنْ عَبْدِ الْمَلِكِ بْنِ أَبِي زُهَيْرٍ الثَّقَفِيِّ، أَنَّ حَمْزَةَ بْنَ عَبْدِ اللَّهِ بْنِ أَبِي أَسْمَاءَ، أَخْبَرَهُ، أَنَّ الْقَاسِمَ بْنَ الْحَسَنِ الثَّقَفِيَّ، أَخْبَرَهُ أَنَّ عَبْدَ اللَّهِ بْنَ جَعْفَرٍ أَخْبَرَهُ أَنَّهُ سَمِعَ رَسُولَ اللَّهِ صَلَّى اللهُ عَلَيْهِ وَسَلَّمَ يَقُولُ: «§أَوَّلُ مَنْ أَشْفَعُ لَهُ مِنْ أُمَّتِي أَهْلُ الْمَدِينَةِ وَأَهْلُ مَكَّةَ وَأَهْلُ الطَّائِفِ»",
            "page": "105",
            "part": "1",
            "seal": "2E289FB1"
        },
        {
            "hno": null,
            "id": "152",
            "nass": "§بَابُ أَوَّلِ قَسَامَةٍ فِي الْإِسْلَامِ",
            "page": "106",
            "part": "1",
            "seal": "AAB47179"
        },
        {
            "hno": "77",
            "id": "153",
            "nass": "77 - حَدَّثَنَا عَلِيُّ بْنُ عَبْدِ الْعَزِيزِ، حَدَّثَنَا أَبُو مَعْمَرٍ، حَدَّثَنَا عَبْدُ الْوَارِثِ بْنُ سَعِيدٍ، عَنْ قَطَنٍ أَبِي الْهَيْثَمِ، عَنْ أَبِي يَزِيدَ الْمَدَنِيِّ، عَنْ عِكْرِمَةَ، عَنِ ابْنِ عَبَّاسٍ، قَالَ: «§أَوَّلُ قَسَامَةٍ كَانَتْ فِي الْإِسْلَامِ، قَسَامَةُ بَنِي هَاشِمٍ»",
            "page": "106",
            "part": "1",
            "seal": "072CDC14"
        },
        {
            "hno": null,
            "id": "154",
            "nass": "§بَابُ أَوَّلِ رَأْسٍ أُهْدِيَ فِي الْإِسْلَامِ",
            "page": "107",
            "part": "1",
            "seal": "7099A5A9"
        },
        {
            "hno": "78",
            "id": "155",
            "nass": "78 - حَدَّثَنَا إِبْرَاهِيمُ بْنُ شَرِيكٍ الْأَسَدِيُّ، حَدَّثَنَا شِهَابُ بْنُ عَبَّادٍ، حَدَّثَنَا شَرِيكٌ، عَنْ أَبِي إِسْحَاقَ، عَنْ هُنَيْدَةَ بْنِ خَالِدٍ الْخُزَاعِيِّ قَالَ: «§أَوَّلُ رَأْسٍ أُهْدِيَ فِي الْإِسْلَامِ رَأْسُ عَمْرِو بْنِ الْحَمِقِ أُهْدِيَ إِلَى مُعَاوِيَةَ»",
            "page": "107",
            "part": "1",
            "seal": "735FCA9E"
        },
        {
            "hno": null,
            "id": "156",
            "nass": "§بَابُ أَوَّلِ مَنْ سَنَّ الرَّكْعَتَيْنِ عِنْدَ الْقَتْلِ",
            "page": "108",
            "part": "1",
            "seal": "0E118611"
        },
        {
            "hno": "79",
            "id": "157",
            "nass": "79 - حَدَّثَنَا الدَّبَرِيُّ، عَنْ عَبْدِ الرَّزَّاقِ، عَنْ مَعْمَرٍ، عَنِ الزُّهْرِيِّ، عَنْ عَمْرِو بْنِ أَبِي سُفْيَانَ الثَّقَفِيِّ، عَنْ أَبِي هُرَيْرَةَ أَنَّ خُبَيْبَ بْنَ عَدِيٍّ، رَضِيَ اللَّهُ عَنْهُ لَمَّا أَرَادَ الْمُشْرِكُونَ قَتْلَهُ قَالَ لَهُمْ: «دَعُونِي أُصَلِّي رَكْعَتَيْنِ» فَتَرَكُوهُ فَصَلَّاهُمَا فَكَانَ §خُبَيْبٌ أَوَّلَ مَنْ سَنَّ الرَّكْعَتَيْنِ عِنْدَ الْقَتْلِ",
            "page": "108",
            "part": "1",
            "seal": "B1B235F5"
        },
        {
            "hno": null,
            "id": "158",
            "nass": "§بَابُ أَوَّلِ مَنْ بَنَى مَسْجِدًا يُصَلِّي فِيهِ فِي الْإِسْلَامِ",
            "page": "109",
            "part": "1",
            "seal": "7ACAE149"
        },
        {
            "hno": "80",
            "id": "159",
            "nass": "80 - حَدَّثَنَا عَلِيُّ بْنُ عَبْدِ الْعَزِيزِ، حَدَّثَنَا أَبُو نُعَيْمٍ، حَدَّثَنَا الْمَسْعُودِيُّ، عَنِ الْقَاسِمِ بْنِ عَبْدِ الرَّحْمَنِ، قَالَ: «§أَوَّلُ مَنْ بَنَى مَسْجِدًا فَصَلَّى فِيهِ عَمَّارُ بْنُ يَاسِرٍ»",
            "page": "109",
            "part": "1",
            "seal": "D4A88FDA"
        },
        {
            "hno": null,
            "id": "160",
            "nass": "§بَابُ أَوَّلُ مَا يُرْفَعُ مِنَ النَّاسِ الْخُشُوعُ",
            "page": "110",
            "part": "1",
            "seal": "3B906374"
        },
        {
            "hno": "81",
            "id": "161",
            "nass": "81 - حَدَّثَنَا مُطَّلِبُ بْنُ شُعَيْبٍ الْأَزْدِيُّ، حَدَّثَنَا عَبْدُ اللَّهِ بْنُ صَالِحٍ، حَدَّثَنِي اللَّيْثُ بْنُ سَعْدٍ، حَدَّثَنِي إِبْرَاهِيمُ بْنُ أَبِي عَبْلَةَ، عَنِ الْوَلِيدِ بْنِ عَبْدِ الرَّحْمَنِ الْجَرَشِيِّ، عَنْ جُبَيْرِ بْنِ نُفَيْرٍ، عَنْ عَوْفِ بْنِ مَالِكٍ الْأَشْجَعِيِّ، رَضِيَ اللَّهُ عَنْهُ أَنَّ رَسُولَ اللَّهِ صَلَّى اللهُ عَلَيْهِ وَسَلَّمَ نَظَرَ إِلَى السَّمَاءِ يَوْمًا فَقَالَ: «§هَذَا أَوَانُ رَفْعِ الْعِلْمِ» فَقَالَ لَهُ رَجُلٌ مِنَ الْأَنْصَارِ يُقَالُ لَهُ: زِيَادُ بْنُ لَبِيدٍ: يَا رَسُولَ اللَّهِ يُرْفَعُ الْعِلْمُ وَقَدْ أُثْبِتَ وَوَعَتْهُ الْقُلُوبُ فَقَالَ رَسُولُ اللَّهِ صَلَّى اللهُ عَلَيْهِ وَسَلَّمَ: «إِنْ كُنْتُ لَأَحْسَبُكَ مِنْ أَفْقَهِ أَهْلِ الْمَدِينَةِ» ثُمَّ ذَكَرَ ضَلَالَةَ الْيَهُودِ وَالنَّصَارَى عَلَى مَا فِي أَيْدِيهِمْ مِنْ كِتَابِ اللَّهِ. قَالَ جُبَيْرُ بْنُ نُفَيْرٍ: فَلَقِيتُ شَدَّادَ بْنَ أَوْسٍ الْأَنْصَارِيَّ فَحَدَّثْتُهُ بِحَدِيثِ عَوْفٍ فَقَالَ: صَدَقَ عَوْفٌ أَلَا أُنَبِّئُكَ بِأَوَّلِ ذَلِكَ يُرْفَعُ الْخُشُوعُ حَتَّى لَا تَرَى خَاشِعًا",
            "page": "110",
            "part": "1",
            "seal": "535AE5A7"
        },
        {
            "hno": null,
            "id": "162",
            "nass": "§بَابُ أَوَّلِ مَنْ يُعْطَى كِتَابَهُ بِيَمِينِهِ وَأَوَّلِ مَنْ يُعْطَى بِشِمَالِهِ",
            "page": "112",
            "part": "1",
            "seal": "5D9B458D"
        },
        {
            "hno": "82",
            "id": "163",
            "nass": "82 - حَدَّثَنَا أَحْمَدُ بْنُ دَاوُدَ الْمَكِّيُّ، حَدَّثَنَا حَبِيبُ بْنُ زُرَيْقٍ كَاتِبُ مَالِكٍ، حَدَّثَنَا مُحَمَّدُ بْنُ عَبْدِ اللَّهِ، أَخِي الزُّهْرِيِّ، عَنِ الزُّهْرِيِّ، عَنِ الْقَاسِمِ بْنِ مُحَمَّدٍ، عَنِ ابْنِ عَبَّاسٍ، عَنِ النَّبِيِّ صَلَّى اللهُ عَلَيْهِ وَسَلَّمَ قَالَ: \" §أَوَّلُ مَنْ يُعْطَى كِتَابَهُ بِيَمِينِهِ: أَبُو سَلَمَةَ بْنُ عَبْدِ الْأَسَدِ وَأَوَّلُ مَنْ يُعْطَى كِتَابَهُ بِشِمَالِهِ: أَخُوهُ سُفْيَانُ بْنُ عَبْدِ الْأَسَدِ \"",
            "page": "112",
            "part": "1",
            "seal": "28C94C77"
        },
        {
            "hno": null,
            "id": "164",
            "nass": "§بَابُ أَوَّلِ شَيْءٍ يُحْشَرُ النَّاسُ وَأَوَّلُ شَيْءٍ يَأْكُلُهُ أَهْلُ الْجَنَّةِ",
            "page": "113",
            "part": "1",
            "seal": "DCCAA46B"
        },
        {
            "hno": "83",
            "id": "165",
            "nass": "83 - حَدَّثَنَا مُحَمَّدُ بْنُ الْعَبَّاسِ الْمُؤَدِّبُ، حَدَّثَنَا عَفَّانُ بْنُ مُسْلِمٍ، حَدَّثَنَا حَمَّادُ بْنُ سَلَمَةَ، عَنْ ثَابِتٍ، عَنْ أَنَسٍ،: أَنَّ عَبْدَ اللَّهِ بْنَ سَلَامٍ رَضِيَ اللَّهُ عَنْهُ قَبْلَ أَنْ يُسْلِمَ سَأَلَ النَّبِيَّ صَلَّى اللهُ عَلَيْهِ وَسَلَّمَ، عَنْ §أَوَّلِ شَيْءٍ يُحْشَرُ النَّاسُ قَالَ \" نَارٌ تَخْرُجُ مِنْ عَدَنِ أَبْيَنَ، تَبِيتُ مَعَهُمْ حَيْثُ بَاتُوا وَتَقِيلُ مَعَهُمْ حَيْثُ قَالُوا. قَالَ: وَأَوَّلُ شَيْءٍ يَأْكُلُهُ أَهْلُ الْجَنَّةِ: زِيَادَةُ كَبِدِ ثَوْرِ الْجَنَّةِ الَّذِي كَانَ يَأْكُلُ مِنْ كُلِّ ثِمَارِهَا فَيَجِدُونَ فِيهِ طَعْمَ كُلِّ ثَمَرَةٍ فِي الْجَنَّةِ \"",
            "page": "113",
            "part": "1",
            "seal": "7931E68E"
        },
        {
            "hno": null,
            "id": "166",
            "nass": "§بَابُ أَوَّلِ مَنْ أَفْشَى الْقُرْآنَ مِنْ فِي النَّبِيِّ صَلَّى اللهُ عَلَيْهِ وَسَلَّمَ بِمَكَّةَ",
            "page": "115",
            "part": "1",
            "seal": "98B84568"
        },
        {
            "hno": "84",
            "id": "167",
            "nass": "84 - حَدَّثَنَا عَلِيُّ بْنُ عَبْدِ الْعَزِيزِ، حَدَّثَنَا أَبُو نُعَيْمٍ، حَدَّثَنَا الْمَسْعُودِيُّ، عَنِ الْقَاسِمِ بْنِ عَبْدِ الرَّحْمَنِ، قَالَ: «§أَوَّلُ مَنْ أَفْشَى الْقُرْآنَ مِنْ فِي رَسُولِ اللَّهِ صَلَّى اللهُ عَلَيْهِ وَسَلَّمَ بِمَكَّةَ عَبْدُ اللَّهِ بْنُ مَسْعُودٍ»",
            "page": "115",
            "part": "1",
            "seal": "3BA3BADC"
        },
        {
            "hno": null,
            "id": "168",
            "nass": "§بَابُ أَوَّلِ مَنْ أَذَّنَ",
            "page": "116",
            "part": "1",
            "seal": "C33E3E2F"
        },
        {
            "hno": "85",
            "id": "169",
            "nass": "85 - حَدَّثَنَا عَلِيُّ بْنُ عَبْدِ الْعَزِيزِ، حَدَّثَنَا أَبُو نُعَيْمٍ، حَدَّثَنَا الْمَسْعُودِيُّ، عَنِ الْقَاسِمِ، قَالَ: «§أَوَّلُ مَنْ أَذَّنَ بِلَالٌ»",
            "page": "116",
            "part": "1",
            "seal": "88C9878C"
        },
        {
            "hno": null,
            "id": "170",
            "nass": "§بَابُ أَوَّلِ مَنْ عَدَا بِهِ فَرَسُهُ فِي سَبِيلِ اللَّهِ عَزَّ وَجَلَّ",
            "page": "117",
            "part": "1",
            "seal": "CE57D89F"
        },
        {
            "hno": "86",
            "id": "171",
            "nass": "86 - حَدَّثَنَا عَلِيُّ بْنُ عَبْدِ الْعَزِيزِ، حَدَّثَنَا أَبُو نُعَيْمٍ، حَدَّثَنَا الْمَسْعُودِيُّ، عَنِ الْقَاسِمِ، قَالَ: «§أَوَّلُ مَنْ عَدَا بِهِ فَرَسُهُ فِي سَبِيلِ اللَّهِ الْمِقْدَادُ بْنُ الْأَسْوَدِ»",
            "page": "117",
            "part": "1",
            "seal": "BDE79A8A"
        },
        {
            "hno": null,
            "id": "172",
            "nass": "§بَابُ أَوَّلِ حَيٍّ مِنَ الْعَرَبِ أَدَّوُا الصَّدَقَةَ طَائِعِينَ",
            "page": "118",
            "part": "1",
            "seal": "B0E05A41"
        },
        {
            "hno": "87",
            "id": "173",
            "nass": "87 - حَدَّثَنَا عَلِيُّ بْنُ عَبْدِ الْعَزِيزِ، حَدَّثَنَا أَبُو نُعَيْمٍ، حَدَّثَنَا الْمَسْعُودِيُّ، عَنِ الْقَاسِمِ، قَالَ: \" §أَوَّلُ مَنْ أَدَّوُا الصَّدَقَةَ طَائِعِينَ مِنْ قِبَلِ أَنْفُسِهِمْ: بَنُو عُذْرَةَ بْنِ سَعْدٍ \"",
            "page": "118",
            "part": "1",
            "seal": "3445D5EB"
        },
        {
            "hno": null,
            "id": "174",
            "nass": "§بَابُ أَوَّلِ حَيٍّ آلَفُوا مَعَ رَسُولِ اللَّهِ صَلَّى اللهُ عَلَيْهِ وَسَلَّمَ",
            "page": "119",
            "part": "1",
            "seal": "976F03F8"
        },
        {
            "hno": "88",
            "id": "175",
            "nass": "88 - حَدَّثَنَا عَلِيُّ بْنُ عَبْدِ الْعَزِيزِ، حَدَّثَنَا أَبُو نُعَيْمٍ، حَدَّثَنَا الْمَسْعُودِيُّ، عَنِ الْقَاسِمِ، قَالَ: «§أَوَّلُ حَيٍّ آلَفُوا مَعَ رَسُولِ اللَّهِ صَلَّى اللهُ عَلَيْهِ وَسَلَّمَ جُهَيْنَةُ»",
            "page": "119",
            "part": "1",
            "seal": "8236CD29"
        }
    ],
    "t13002": [
        {
            "id": "1",
            "lvl": "1",
            "sub": null,
            "tit": "باب: أول ما خلق الله القلم"
        },
        {
            "id": "3",
            "lvl": "1",
            "sub": null,
            "tit": "باب: أول ما خلق الله من الإنسان فرجه"
        },
        {
            "id": "5",
            "lvl": "1",
            "sub": null,
            "tit": "باب أن أول من جحد آدم عليه السلام"
        },
        {
            "id": "7",
            "lvl": "1",
            "sub": null,
            "tit": "باب أنا أول من تنشق عنه الأرض يوم القيامة"
        },
        {
            "id": "9",
            "lvl": "1",
            "sub": null,
            "tit": "باب أنا أول من يقرع باب الجنة"
        },
        {
            "id": "11",
            "lvl": "1",
            "sub": null,
            "tit": "باب أنا أول شافع وأول مشفع"
        },
        {
            "id": "13",
            "lvl": "1",
            "sub": null,
            "tit": "باب أنا أول شافع وأول مشفع يوم القيامة"
        },
        {
            "id": "15",
            "lvl": "1",
            "sub": null,
            "tit": "باب أول الأمم يدخل الجنة"
        },
        {
            "id": "17",
            "lvl": "1",
            "sub": null,
            "tit": "باب أول من يكسى يوم القيامة"
        },
        {
            "id": "19",
            "lvl": "1",
            "sub": null,
            "tit": "باب أول من أضاف الضيفان"
        },
        {
            "id": "21",
            "lvl": "1",
            "sub": null,
            "tit": "باب أول من اختتن"
        },
        {
            "id": "23",
            "lvl": "1",
            "sub": null,
            "tit": "باب أول من صنعت له النورة"
        },
        {
            "id": "25",
            "lvl": "1",
            "sub": null,
            "tit": "باب أول الأنبياء عليهم السلام"
        },
        {
            "id": "27",
            "lvl": "1",
            "sub": null,
            "tit": "باب أول من يبعث يوم القيامة من الأمم وأول من يحاسب"
        },
        {
            "id": "29",
            "lvl": "1",
            "sub": null,
            "tit": "باب أول من صافح"
        },
        {
            "id": "31",
            "lvl": "1",
            "sub": null,
            "tit": "باب أول ما بدئ به رسول الله من الوحي"
        },
        {
            "id": "33",
            "lvl": "1",
            "sub": null,
            "tit": "باب أول ما نزل من القرآن"
        },
        {
            "id": "35",
            "lvl": "1",
            "sub": null,
            "tit": "باب أول ما علم جبريل النبي صلى الله عليه وسلم"
        },
        {
            "id": "37",
            "lvl": "1",
            "sub": null,
            "tit": "باب أول من سيب السوائب وبحر البحيرة وغير دين إبراهيم"
        },
        {
            "id": "39",
            "lvl": "1",
            "sub": null,
            "tit": "باب أول ما يتكلم من الإنسان يوم القيامة"
        },
        {
            "id": "41",
            "lvl": "1",
            "sub": null,
            "tit": "باب أول ما ينطق من الإنسان"
        },
        {
            "id": "43",
            "lvl": "1",
            "sub": null,
            "tit": "باب أول ما ينتن من الإنسان في قبره"
        },
        {
            "id": "45",
            "lvl": "1",
            "sub": null,
            "tit": "باب أول ما يحاسب به العبد"
        },
        {
            "id": "47",
            "lvl": "1",
            "sub": null,
            "tit": "باب إن أول ما يقضى به بين الناس في الدماء"
        },
        {
            "id": "49",
            "lvl": "1",
            "sub": null,
            "tit": "باب أول من رمى بسهم في سبيل الله"
        },
        {
            "id": "51",
            "lvl": "1",
            "sub": null,
            "tit": "باب أول من سل سيفا في سبيل الله تعالى"
        },
        {
            "id": "53",
            "lvl": "1",
            "sub": null,
            "tit": "باب أول من قدم المدينة من المهاجرين"
        },
        {
            "id": "55",
            "lvl": "1",
            "sub": null,
            "tit": "باب أول من جمع بالمدينة قبل قدوم رسول الله"
        },
        {
            "id": "57",
            "lvl": "1",
            "sub": null,
            "tit": "باب أول جمعة جمعت في الإسلام في غير المدينة"
        },
        {
            "id": "59",
            "lvl": "1",
            "sub": null,
            "tit": "باب أول آية نزلت في القتال"
        },
        {
            "id": "61",
            "lvl": "1",
            "sub": null,
            "tit": "باب أول زمرة يدخلون الجنة"
        },
        {
            "id": "63",
            "lvl": "1",
            "sub": null,
            "tit": "باب إن أول الآيات طلوع الشمس من مغربها"
        },
        {
            "id": "65",
            "lvl": "1",
            "sub": null,
            "tit": "باب أول من قطع في الإسلام"
        },
        {
            "id": "67",
            "lvl": "1",
            "sub": null,
            "tit": "باب أول ما سمع من رسول الله حين قدم المدينة"
        },
        {
            "id": "69",
            "lvl": "1",
            "sub": null,
            "tit": "باب أول من جدر الكعبة بعد كلاب بن مرة"
        },
        {
            "id": "71",
            "lvl": "1",
            "sub": null,
            "tit": "باب أول من يدخل النار من هذه الأمة"
        },
        {
            "id": "73",
            "lvl": "1",
            "sub": null,
            "tit": "باب أول من يكسى حلة من النار"
        },
        {
            "id": "75",
            "lvl": "1",
            "sub": null,
            "tit": "باب أول من يرد على النبي حوضه"
        },
        {
            "id": "77",
            "lvl": "1",
            "sub": null,
            "tit": "باب أول من يرد الحوض بعد هذه الطبقة"
        },
        {
            "id": "79",
            "lvl": "1",
            "sub": null,
            "tit": "باب أول من قال أما بعد"
        },
        {
            "id": "81",
            "lvl": "1",
            "sub": null,
            "tit": "باب أول من كتب بسم الله الرحمن الرحيم"
        },
        {
            "id": "84",
            "lvl": "1",
            "sub": null,
            "tit": "باب أول ما كان يلقي جبريل على رسول الله صلى الله عليه وسلم إذا نزل الوحي \" بسم الله الرحمن الرحيم \""
        },
        {
            "id": "86",
            "lvl": "1",
            "sub": null,
            "tit": "باب أول ما أنزل من التوراة بسم الله الرحمن الرحيم"
        },
        {
            "id": "88",
            "lvl": "1",
            "sub": null,
            "tit": "باب أول من شاب"
        },
        {
            "id": "90",
            "lvl": "1",
            "sub": null,
            "tit": "باب أول ما فرضت الصلاة"
        },
        {
            "id": "92",
            "lvl": "1",
            "sub": null,
            "tit": "باب أول من سن القتل"
        },
        {
            "id": "94",
            "lvl": "1",
            "sub": null,
            "tit": "باب أول من عرف رسول الله لما فقده أصحابه يوم أحد"
        },
        {
            "id": "96",
            "lvl": "1",
            "sub": null,
            "tit": "باب أول ما يكفأ الدين"
        },
        {
            "id": "98",
            "lvl": "1",
            "sub": null,
            "tit": "باب أول جدة أعطاها رسول الله صلى الله عليه وسلم"
        },
        {
            "id": "100",
            "lvl": "1",
            "sub": null,
            "tit": "باب إن أول من أسلم علي بن أبي طالب"
        },
        {
            "id": "102",
            "lvl": "1",
            "sub": null,
            "tit": "باب أول من أسلم"
        },
        {
            "id": "104",
            "lvl": "1",
            "sub": null,
            "tit": "باب أول من أسلم"
        },
        {
            "id": "106",
            "lvl": "1",
            "sub": null,
            "tit": "باب من قال خديجة ثم علي رضي الله عنهما"
        },
        {
            "id": "108",
            "lvl": "1",
            "sub": null,
            "tit": "باب من قال أول من أسلم أبو بكر رضي الله عنه"
        },
        {
            "id": "110",
            "lvl": "1",
            "sub": null,
            "tit": "باب أول خبر جاء المدينة بمبعث رسول الله صلى الله عليه وسلم"
        },
        {
            "id": "112",
            "lvl": "1",
            "sub": null,
            "tit": "باب أول أهل رسول الله كان أسرع به لحوقا"
        },
        {
            "id": "114",
            "lvl": "1",
            "sub": null,
            "tit": "باب أول الناس هلاكا"
        },
        {
            "id": "116",
            "lvl": "1",
            "sub": null,
            "tit": "باب أول حبس كان في الإسلام"
        },
        {
            "id": "118",
            "lvl": "1",
            "sub": null,
            "tit": "باب أول من أسلم من العرب بعد الأنصار"
        },
        {
            "id": "120",
            "lvl": "1",
            "sub": null,
            "tit": "باب أي المدينتين يفتح أولا قسطنطينية أو رومية"
        },
        {
            "id": "122",
            "lvl": "1",
            "sub": null,
            "tit": "باب أول أمير أمر في الإسلام"
        },
        {
            "id": "124",
            "lvl": "1",
            "sub": null,
            "tit": "باب أول من فاء من أصحاب رسول الله صلى الله عليه وسلم بعد الهزيمة يوم أحد"
        },
        {
            "id": "126",
            "lvl": "1",
            "sub": null,
            "tit": "باب أول ما ظهر من إيمان النجاشي رحمه الله"
        },
        {
            "id": "128",
            "lvl": "1",
            "sub": null,
            "tit": "باب أول من يسمع نفخة الصور يوم القيامة"
        },
        {
            "id": "130",
            "lvl": "1",
            "sub": null,
            "tit": "باب أول ما يقول الله للمؤمنين يوم القيامة"
        },
        {
            "id": "132",
            "lvl": "1",
            "sub": null,
            "tit": "باب أول من يجيز على الصراط يوم القيامة"
        },
        {
            "id": "134",
            "lvl": "1",
            "sub": null,
            "tit": "باب أول ما تفوه به النبي في حجة الوداع"
        },
        {
            "id": "136",
            "lvl": "1",
            "sub": null,
            "tit": "باب أول مولود ولد في الإسلام بالمدينة"
        },
        {
            "id": "138",
            "lvl": "1",
            "sub": null,
            "tit": "باب أول مولود صغير دخل بطنه ريق النبي صلى الله عليه وسلم"
        },
        {
            "id": "140",
            "lvl": "1",
            "sub": null,
            "tit": "باب أول من أصيب من الأنصار يوم بدر"
        },
        {
            "id": "142",
            "lvl": "1",
            "sub": null,
            "tit": "باب أول من ذهب عنه النعاس يوم بدر"
        },
        {
            "id": "144",
            "lvl": "1",
            "sub": null,
            "tit": "باب أول من طعن يوم بئر معونة"
        },
        {
            "id": "146",
            "lvl": "1",
            "sub": null,
            "tit": "باب أين كانت أول شكوى رسول الله الأخيرة"
        },
        {
            "id": "148",
            "lvl": "1",
            "sub": null,
            "tit": "باب أي مسجد وضع في الأرض أول"
        },
        {
            "id": "150",
            "lvl": "1",
            "sub": null,
            "tit": "باب أول من يشفع له رسول الله صلى الله عليه وسلم من أمته"
        },
        {
            "id": "152",
            "lvl": "1",
            "sub": null,
            "tit": "باب أول قسامة في الإسلام"
        },
        {
            "id": "154",
            "lvl": "1",
            "sub": null,
            "tit": "باب أول رأس أهدي في الإسلام"
        },
        {
            "id": "156",
            "lvl": "1",
            "sub": null,
            "tit": "باب أول من سن الركعتين عند القتل"
        },
        {
            "id": "158",
            "lvl": "1",
            "sub": null,
            "tit": "باب أول من بنى مسجدا يصلي فيه في الإسلام"
        },
        {
            "id": "160",
            "lvl": "1",
            "sub": null,
            "tit": "باب أول ما يرفع من الناس الخشوع"
        },
        {
            "id": "162",
            "lvl": "1",
            "sub": null,
            "tit": "باب أول من يعطى كتابه بيمينه وأول من يعطى بشماله"
        },
        {
            "id": "164",
            "lvl": "1",
            "sub": null,
            "tit": "باب أول شيء يحشر الناس وأول شيء يأكله أهل الجنة"
        },
        {
            "id": "166",
            "lvl": "1",
            "sub": null,
            "tit": "باب أول من أفشى القرآن من في النبي صلى الله عليه وسلم بمكة"
        },
        {
            "id": "168",
            "lvl": "1",
            "sub": null,
            "tit": "باب أول من أذن"
        },
        {
            "id": "170",
            "lvl": "1",
            "sub": null,
            "tit": "باب أول من عدا به فرسه في سبيل الله عز وجل"
        },
        {
            "id": "172",
            "lvl": "1",
            "sub": null,
            "tit": "باب أول حي من العرب أدوا الصدقة طائعين"
        },
        {
            "id": "174",
            "lvl": "1",
            "sub": null,
            "tit": "باب أول حي آلفوا مع رسول الله صلى الله عليه وسلم"
        }
    ]
}